Workbook

Sheet Coding Log
A1: CSC 808 Phase 2 Inductive QUAL Coding Log | Rambel Stone | April 2026
A2: Corpus: 47 documents | Codebook v1.0 | Constant comparative method | κ subsample: 16 docs, seed=808, Pass 1 / Pass 2 (≥14-day gap) | κ ≥ 0.70 required
A3: Entry # | B3: Doc # (registry) | C3: Document title (short) | D3: Year | E3: Source | F3: Artifact type | G3: Coding unit | H3: Page / section ref | I3: Passage text (extracted) | J3: Code 1 | K3: Code 2 | L3: Code 3 | M3: CRS flag | N3: Code 1 rationale | O3: Code 2 rationale | P3: Pass | Q3: κ subsample? | R3: Memo / analytic note | S3: source_detail | T3: artifact_type_review_flag | U3: kappa_status | V3: kappa_note
A4: 1 | B4: 39 | C4: SWGDE Overview: Artificial Intelligence Trends in Video Analysis (v1.0) | D4: 2021 | E4: SWGDE Video | F4: Published Document (AI-specific) PRIORITY | G4: Full document | H4: §3 Limitations, p.3 | I4: "not intended to state a position for or against the use of artificial intelligence...offered solely as an informational overview" | J4: ORG-01 | M4: CRS-02 | P4: Pass 1 | Q4: Yes | U4: in
A5: 2 | B5: 39 | C5: SWGDE Overview: Artificial Intelligence Trends in Video Analysis (v1.0) | D5: 2021 | E5: SWGDE Video | F5: Published Document (AI-specific) PRIORITY | G5: Full document | H5: §3 Limitations, p.3 | I5: "implemented only after consultation with legal personnel versed in the laws and rules applicable to the investigator's particular jurisdiction" | J5: ORG-06 | P5: Pass 1 | Q5: Yes | U5: in
A6: 3 | B6: 39 | C6: SWGDE Overview: Artificial Intelligence Trends in Video Analysis (v1.0) | D6: 2021 | E6: SWGDE Video | F6: Published Document (AI-specific) PRIORITY | G6: Full document | H6: §6.4, p.7 | I6: known examples of bias...any results/identification should be confirmed by a properly trained examiner before action is taken | J6: TEC-01 | M6: CRS-02 | P6: Pass 1 | Q6: Yes | U6: in
A7: 4 | B7: 39 | C7: SWGDE Overview: Artificial Intelligence Trends in Video Analysis (v1.0) | D7: 2021 | E7: SWGDE Video | F7: Published Document (AI-specific) PRIORITY | G7: Full document | H7: §7.4.1, p.1 | I7: "any results obtained through the use of ML-based data comparisons require human verification...before legal action is taken" | J7: CRS-02 | K7: TEC-02 | P7: Pass 1 | Q7: Yes | R7: "Cold read suggests possible reclassification. Consider CRS-02 as Code 1 with TEC-02 as Code 2. Verify in Pass 2." | U7: in
A8: 5 | B8: 39 | C8: SWGDE Overview: Artificial Intelligence Trends in Video Analysis (v1.0) | D8: 2021 | E8: SWGDE Video | F8: Published Document (AI-specific) PRIORITY | G8: Full document | H8: §7.4.3, p.11 | I8: "especially difficult for Computer Vision applications that adapt...algorithms developed for proprietary tools are unknown and require benchmarking" | J8: TEC-02 | K8: TEC-06 | P8: Pass 1 | Q8: Yes | U8: in
A9: 6 | B9: 39 | C9: SWGDE Overview: Artificial Intelligence Trends in Video Analysis (v1.0) | D9: 2021 | E9: SWGDE Video | F9: Published Document (AI-specific) PRIORITY | G9: Full document | H9: §7.4.3, p.11 | I9: "should provide limited statistical evaluation for false positives and negatives...results given at one point in time are able to be repeated" | J9: TEC-01 | M9: CRS-02 | P9: Pass 1 | Q9: Yes | U9: in
A10: 7 | B10: 39 | C10: SWGDE Overview: Artificial Intelligence Trends in Video Analysis (v1.0) | D10: 2021 | E10: SWGDE Video | F10: Published Document (AI-specific) PRIORITY | G10: Full document | H10: §10 History, p.15 | I10: 2.5-year revision cycle (Sept 2018 – Jan 2021), 9 editing sessions, no prescriptive output produced | J10: PRO-02 | P10: Pass 1 | Q10: Yes | R10: Flag column R (memo note) for entry 7: Dominant pattern: ORG-01 as structural frame; TEC-01/TEC-06 recurring in validation sections; CRS-02 consistent throughout. 2.5-year history with zero prescriptive output. | U10: in
A11: 8 | B11: 38 | C11: SWGDE Position on Facial Recognition and Facial Comparison Development and Com | D11: 2022 | E11: SWGDE Imaging | F11: Position Document (published) | G11: Full document | H11: §3 FRS def., p.1 | I11: "not meant to be a step-by-step guide...refer to FISWG" | J11: ORG-01 | N11: Strong | P11: Pass 1 | Q11: No | R11: Strong | U11: out
A12: 9 | B12: 38 | C12: SWGDE Position on Facial Recognition and Facial Comparison Development and Com | D12: 2022 | E12: SWGDE Imaging | F12: Position Document (published) | G12: Full document | H12: §4, p.2 | I12: "algorithm performance entirely dependent upon patterns...do not correlate to obvious anatomical features" | J12: TEC-06 | M12: CRS-01 | N12: Strong | P12: Pass 1 | R12: Strong
A13: 10 | B13: 38 | C13: SWGDE Position on Facial Recognition and Facial Comparison Development and Com | D13: 2022 | E13: SWGDE Imaging | F13: Position Document (published) | G13: Full document | H13: §4, p.2 | I13: "facial recognition candidate returns are not considered a positive identification...trained human adjudication" | J13: CRS-02 | N13: Provisional | P13: Pass 2 | R13: TEC-01 provisional
A14: 11 | B14: 38 | C14: SWGDE Position on Facial Recognition and Facial Comparison Development and Com | D14: 2022 | E14: SWGDE Imaging | F14: Position Document (published) | G14: Full document | H14: §4, p.2 | I14: "facial comparison does not provide positive identifications...standardized scale" | J14: TEC-01 | N14: Provisional | P14: Pass 1 | R14: TEC-03 provisional "?". NOTE reclassifying entry 11 from TEC-03 to CRS-02 in Pass 2. Note in memo column now. "Cold read suggests possible reclassification from TEC-03 to CRS-02 in Pass 2. Standardized scale is acknowledged but not specified this may be a language choice rather than unresolved technical consensus."
A15: 12 | B15: 38 | C15: SWGDE Position on Facial Recognition and Facial Comparison Development and Com | D15: 2022 | E15: SWGDE Imaging | F15: Position Document (published) | G15: Full document | H15: §4, p.2 | I15: "results must be reviewed by trained personnel...not the only basis for law enforcement action" | J15: ORG-06 | M15: CRS-02 | N15: Strong | P15: Pass 1 | R15: Strong
A16: 13 | B16: 38 | C16: SWGDE Position on Facial Recognition and Facial Comparison Development and Com | D16: 2022 | E16: SWGDE Imaging | F16: Position Document (published) | G16: Full document | H16: §6 History, p.3 | I16: Three consecutive Draft for Public Comment iterations (June 2021, Sept 2021, Jan 2022) | J16: PRO-01 | M16: CRS-01 | N16: Strong | P16: Pass 1 | R16: Strong
A17: 14 | B17: C1 | C17: NIST OSAC FSSB Meeting Agendas Public Sessions (2023, multiple quarters) | D17: 2023 | E17: NIST OSAC | F17: Meeting Agenda (Public) | G17: Full document | H17: Item 4, Task Groups | I17: Complete Task Group roster no AI or confidence measurement task group in FSSB governance | J17: ORG-07 | N17: Strong | P17: Pass 1 | Q17: No | R17: Strong confirmed across all 4 quarters: no AI TG added at any point in 2023 | U17: out
A18: 15 | B18: C1 | C18: NIST OSAC FSSB Meeting Agendas Public Sessions (2023, multiple quarters) | D18: 2023 | E18: NIST OSAC | F18: Meeting Agenda (Public) | G18: Full document | H18: Standards pipeline, Day 2 | I18: Full standards pipeline no AI standards in registry review, petition, or open comment | J18: ORG-07 | N18: Strong | P18: Pass 1 | R18: Strong confirmed cross-quarter: no AI standards in pipeline Q1–Q4
A19: 16 | B19: C1 | C19: NIST OSAC FSSB Meeting Agendas Public Sessions (2023, multiple quarters) | D19: 2023 | E19: NIST OSAC | F19: Meeting Agenda (Public) | G19: Full document | H19: Item 6c-iv, D/M SAC | I19: "Digital/Multimedia Technical Guidance Request [Vote]" only D/M action item in full year | J19: ORG-03 | N19: Provisional | P19: Pass 1 | R19: Provisional "?" content of request not visible. Still provisional "?". This cannot be resolved without knowing what the vote covered. Hold at ORG-03 "?" until C5 or other C1 documents provide context.
A20: 17 | B20: C1 | C20: NIST OSAC FSSB Meeting Agendas Public Sessions (2023, multiple quarters) | D20: 2023 | E20: NIST OSAC | F20: Meeting Agenda (Public) | G20: Full document | H20: OPO Item 3 | I20: R&D Needs Update recurring information-only item, no D/M or AI escalation visible | J20: ORG-07 | N20: Provisional | P20: Pass 1 | R20: Provisional "?" cross-document support needed from C5. retain ORG-07 but note in memo that entry 22 provides the stronger empirical confirmation of this pattern. Entries 17 and 22 together form one finding, not two independent findings.
A21: 18 | B21: C1 | C21: NIST OSAC FSSB Meeting Agendas Public Sessions (2023, multiple quarters) | D21: 2023 | E21: NIST OSAC | F21: Meeting Agenda (Public) | G21: Full document | H21: Item 24, Day 2 | I21: "Interpretation Scales FSSB Discussion: Chemistry: Trace Evidence, Physics/Pattern" Digital/Multimedia excluded | J21: ORG-05 | N21: Strong | P21: Pass 2 | R21: Strong on ORG-05; ORG-03 provisional "?". Pass 2, consider dropping ORG-03 from this entry and keeping ORG-05 only unless you find evidence the D/M exclusion was a priority decision rather than a scope decision.
A22: 19 | B22: 1 | C22: NIST AI RMF Development Public Comments Received During RFC Period | D22: 2023 | E22: NIST AI | F22: Public Comment Record | G22: Full document | H22: Section Level | I22: NIST AI RMF RFC public comment record inaccessible EO 14110 rescinded Jan 20 2025; NIST site search returns no results; associated comment archive delisted | J22: PRO-02 | K22: ORG-05 | N22: Possible Emerging | P22: Pass 1 | Q22: No | R22: Entry 19 (EO 14110 rescission rendering NIST AI RMF RFC inaccessible) does not fit cleanly into any existing code. PRO-02 + ORG-05 captures it partially but misses the specifically political and external nature of the barrier. This is still a candidate for EMER-01. The question is whether this pattern recurs. If you find other instances of AI governance records being rendered inaccessible by political action in your remaining 42 documents, activate EMER-01. If entry 19 remains the only instance, it is better described as an unusual PRO-02 than as a new category. Hold EMER-01 do not activate yet. | U22: out
A23: 20 | B23: 16 | C23: NIST OSAC Annual Reports Digital/Multimedia SAC (2020, 2021, 2022, 2023) [consolidated from orig. #16–19] | D23: 2020–2023 | E23: NIST OSAC | F23: Annual Report / Organizational Newsletter | G23: Full document | H23: Section Level | I23: Document-level access finding | J23: ORG-05 | N23: Strong | P23: Pass 1 | R23: OSAC annual reports not consistently published or archived 2020 and 2022 inaccessible. Institutional transparency gap limits external accountability for Digital/Multimedia standards governance.
A24: 21 | B24: 16 | C24: NIST OSAC Annual Reports Digital/Multimedia SAC (2020, 2021, 2022, 2023) [consolidated from orig. #16–19] | D24: 2020–2023 | E24: NIST OSAC | F24: Annual Report / Organizational Newsletter | G24: Full document | H24: Section Level | I24: table"Digital Evidence +2 Published (1st SWGDE documents!)" FY23 first SWGDE entry in 9 years | J24: ORG-05 | N24: Strong | P24: Pass 1
A25: 22 | B25: 16 | C25: NIST OSAC Annual Reports Digital/Multimedia SAC (2020, 2021, 2022, 2023) [consolidated from orig. #16–19] | D25: 2020–2023 | E25: NIST OSAC | F25: Annual Report / Organizational Newsletter | G25: Full document | H25: Section Level | I25: "There are no research and development needs identified by the Digital Evidence Subcommittee" | J25: ORG-07 | N25: Strongest ORG-07 in corpus | P25: Pass 1 | Q25: No | U25: out
A26: 23 | B26: 16 | C26: NIST OSAC Annual Reports Digital/Multimedia SAC (2020, 2021, 2022, 2023) [consolidated from orig. #16–19] | D26: 2020–2024 | E26: NIST OSAC | F26: Annual Report / Organizational Newsletter | G26: Full document | H26: Section Level | I26: ANSI/ASTM E3016-18 confidence standard pending OSAC registry acceptance since 2018 (6+ years) | J26: PRO-02 | K26: PRO-06 | N26: Strongest PRO-02 in corpus | P26: Pass 1 | R26: Action: Recoded entry 23 from PRO-02 to PRO-06, or assign both. PRO-06 is more precise here because the standard exists and is published the failure is in the adoption pathway between the SDO and the governance registry, which is a coordination gap rather than a process stall. Write a decision log entry explaining this distinction.
A27: 24 | B27: 16 | C27: NIST OSAC Annual Reports Digital/Multimedia SAC (2020, 2021, 2022, 2023) [consolidated from orig. #16–19] | D27: 2020–2025 | E27: NIST OSAC | F27: Annual Report / Organizational Newsletter | G27: Full document | H27: Section Level | I27: Generative AI tools reference document informational only, no prescriptive requirements | J27: ORG-01 | N27: Strong | P27: Pass 1 | Q27: Yes | U27: in
A28: 25 | B28: 16 | C28: NIST OSAC Annual Reports Digital/Multimedia SAC (2020, 2021, 2022, 2023) [consolidated from orig. #16–19] | D28: 2020–2026 | E28: NIST OSAC | F28: Annual Report / Organizational Newsletter | G28: Full document | H28: Section Level | I28: "Is this a Deepfake?" both versions listed as "being updated," no publication date | J28: PRO-03 | N28: Strong | P28: Pass 1
A29: =IF(I29<>"",ROW()-3,"") -> 26 | B29: 42 | C29: SWGDE Best Practices for Digital Evidence Acquisition from Cloud Service Providers (v1.0) | D29: 2020 | E29: SWGDE Forensics | F29: Draft Released for Comment | G29: Full document | H29: §3 Limitations, p.4 | I29: "Due to the vast number of emerging platforms and cloud service providers, it is not possible to establish a precise set of procedures to cover every situation...This document identifies the high-level considerations and steps for the collection of cloud based digital evidence." | J29: ORG-01 | N29: Strong explicit scope exclusion; precision procedures deferred to examiner judgment; no confidence metric or AI-specific content follows from this framing | P29: Pass 1 | Q29: Yes | U29: in
A30: =IF(I30<>"",ROW()-3,"") -> 27 | B30: 42 | C30: SWGDE Best Practices for Digital Evidence Acquisition from Cloud Service Providers (v1.0) | D30: 2020 | E30: SWGDE Forensics | F30: Draft Released for Comment | G30: Full document | H30: §3 Limitations, p.4 | I30: "Guidance in this document is not meant to replace legal guidance from a responsible legal professional, nor is it meant to cover every conceivable situation." | J30: ORG-06 | N30: Legal constraint as structural ceiling on guidance specificity mirrors Doc #38 dominant pattern; legal deference prevents prescriptive output | P30: Pass 1 | Q30: Yes | U30: in
A31: =IF(I31<>"",ROW()-3,"") -> 28 | B31: 42 | C31: SWGDE Best Practices for Digital Evidence Acquisition from Cloud Service Providers (v1.0) | D31: 2020 | E31: SWGDE Forensics | F31: Draft Released for Comment | G31: Full document | H31: §9 Steps After Acquisition, p.10 | I31: "Compute and record hash values for the acquired data. If a provider has digitally signed their production or provided hash values, verify the signature or hash values." | J31: TEC-03 | M31: CRS-02 | N31: Hash verification is the only quantifiable integrity mechanism in the document a procedural integrity check, not a confidence metric; contingent on provider cooperation | P31: Pass 1 | Q31: Yes | U31: in
A32: =IF(I32<>"",ROW()-3,"") -> 29 | B32: 42 | C32: SWGDE Best Practices for Digital Evidence Acquisition from Cloud Service Providers (v1.0) | D32: 2020 | E32: SWGDE Forensics | F32: Draft Released for Comment | G32: Full document | H32: §6.2 / §8 During Acquisition, pp.6, 9 | I32: "If the cloud service does not provide an export tool, the collector should document specific steps taken or tools utilized...If all methods fail, consider screen captures or photographs of the relevant data." | J32: TEC-02 | K32: PRO-02 | N32: Validation methodology absent; fallback to screen captures/photographs as last resort no validated acquisition standard exists for heterogeneous cloud environments | O32: Process stall document cannot converge on prescriptive acquisition protocol; provider environment heterogeneity prevents standardization | P32: Pass 1 | Q32: Yes | U32: in
A33: =IF(I33<>"",ROW()-3,"") -> 30 | B33: 42 | C33: SWGDE Best Practices for Digital Evidence Acquisition from Cloud Service Providers (v1.0) | D33: 2020 | E33: SWGDE Forensics | F33: Draft Released for Comment | G33: Full document | H33: §10 History, p.11 | I33: Draft June 2019 → public comment period → no edits following comment period → approved September 2019 → re-voted final publication September 2020. Zero substantive changes after public comment. | J33: PRO-01 | N33: Multi-stage public comment process produced zero substantive changes no confidence measurement content added at any revision stage across 14-month publication cycle | P33: Pass 1 | Q33: Yes | R33: Doc 42 dominant pattern: ORG-01 + ORG-06 co-occurrence in §3 now confirmed third consecutive SWGDE document with this dual exclusion opening (Docs #36, #38, #42). Hash verification (TEC-03/CRS-02) in §9 is only integrity mechanism contingent on provider cooperation, reinforcing ORG-02 resource constraint theme. PRO-01 history: zero edits after public comment mirrors Doc #38 three-iteration pattern. Leanest codeable document in corpus almost entirely legal/procedural scaffolding. | U33: in
A34: 31 | B34: 36 | C34: SWGDE Best Practices for On-Scene ID, Seizure & Preservation of IoT Devices (22-F-001-1.0) | D34: 2022 | E34: SWGDE Forensics | F34: Draft Released for Comment | G34: Full document | H34: §1 Purpose / §2 Scope, pp.2 | I34: "not intended to be a training manual or a specific operating procedure...not all-inclusive" procedural guidance scoped to on-scene only; cloud, analytics, and AI tool validation explicitly excluded | J34: ORG-01 | N34: Strong explicit scope exclusion language limits document to field identification/seizure; AI tool output validation and confidence measurement are outside stated scope | P34: Pass 1 | Q34: Yes | R34: Doc 36 dominant pattern: ORG-01 (scope exclusion) as primary frame AI/confidence measurement excluded by design, not omission. TEC-01/TEC-02 present in preservation/collection sections without resolution. ORG-02 + PRO-02 co-occur in §9 confirming resource-process barrier dyad. Zero prescriptive confidence output. Compare with Doc #39 (informational positioning) and Doc #38 (legal constraint framing) Doc 36 adds a third SWGDE exclusion logic: operational scope. | U34: in
A35: 32 | B35: 36 | C35: SWGDE Best Practices for On-Scene ID, Seizure & Preservation of IoT Devices (22-F-001-1.0) | D35: 2022 | E35: SWGDE Forensics | F35: Draft Released for Comment | G35: Full document | H35: §7 Collection, pp.7–8 | I35: Artifact/Data Spoliation "Specific Considerations/Cautions (Instances where probative data exists in volatile memory only or where data overwrites or appends in a finite storage setting)" no error rate or confidence metric specified | J35: TEC-01 | M35: CRS-02 | N35: Acknowledges data integrity risk (volatile memory, finite storage overwrite) but provides no quantitative confidence metric or error rate gap identified, not addressed | P35: Pass 1 | Q35: Yes | U35: in
A36: 33 | B36: 36 | C36: SWGDE Best Practices for On-Scene ID, Seizure & Preservation of IoT Devices (22-F-001-1.0) | D36: 2022 | E36: SWGDE Forensics | F36: Draft Released for Comment | G36: Full document | H36: §8 Preservation, pp.9 | I36: "Just as the integrity of the data of more traditional devices needs to be preserved through write-blocking or other means, IoT devices and associated applications similarly need information protected and preserved" analogical framing, no IoT-specific validation protocol specified | J36: TEC-02 | N36: Recognizes that IoT preservation requires equivalent rigor to traditional digital forensics but offers no IoT-specific validation methodology gap acknowledged via analogy without resolution | P36: Pass 1 | Q36: Yes | U36: in
A37: 34 | B37: 36 | C37: SWGDE Best Practices for On-Scene ID, Seizure & Preservation of IoT Devices (22-F-001-1.0) | D37: 2022 | E37: SWGDE Forensics | F37: Draft Released for Comment | G37: Full document | H37: §9 Other Considerations, pp.9 | I37: "One of the major challenges in data acquisition from IoT devices is the lack of available training, tools, research documents, and collection procedures. Manufacturers may be reluctant to provide assistance..." | J37: ORG-02 | K37: PRO-02 | N37: Resource constraint explicit acknowledgment of tool/training/documentation gap as primary barrier to forensic capability in this domain | O37: Process stall absence of validated collection procedures is framed as current state, not as a development roadmap; no timeline or prescription for resolution | P37: Pass 1 | Q37: Yes | R37: Doc 36 dominant pattern: ORG-01 (scope exclusion) as primary frame AI/confidence measurement excluded by design, not omission. TEC-01/TEC-02 present in preservation/collection sections without resolution. ORG-02 + PRO-02 co-occur in §9 confirming resource-process barrier dyad. Zero prescriptive confidence output. Compare with Doc #39 (informational positioning) and Doc #38 (legal constraint framing) Doc 36 adds a third SWGDE exclusion logic: operational scope. | U37: in
A38: 35 | B38: 34 | C38: SWGDE Training Guidelines for Video/Image Analysis and Photography | D38: 2019 | E38: SWGDE | F38: Training Guidelines | G38: Full document | H38: §1 Purpose §4 Limitations | I38: "provide guidelines and recommendations…program should demonstrate and document the training selected is adequate to ensure competency" | J38: ORG-01 | K38: — | L38: CRS-02 | N38: Document-level pattern: ORG-01 (scope exclusion) + TEC-01 (measurement complexity) are co-dominant. TEC-02 present at §5. PRO-01 confirmed via revision history. No AI-specific content (publication date 2016). CRS-02 flags cluster around §3, §9, and §10.5/10.7 competency/proficiency definitions acknowledge measurement without operationalizing it. | Scope exclusion | [code_3]: "Adequate to ensure competency" confidence-adjacent, no quantitative grounding | P38: Pass 1 | Q38: Yes | U38: in
A39: 36 | B39: 34 | C39: SWGDE Training Guidelines for Video/Image Analysis and Photography | D39: 2019 | E39: SWGDE | F39: Training Guidelines | G39: Full document | H39: §3 Terminology | I39: Competency = "evaluation of knowledge and ability…prior to independent completion"; Proficiency = "evaluation of quality of performance" | J39: TEC-01 | K39: — | L39: — | N39: Document-level pattern: ORG-01 (scope exclusion) + TEC-01 (measurement complexity) are co-dominant. TEC-02 present at §5. PRO-01 confirmed via revision history. No AI-specific content (publication date 2016). CRS-02 flags cluster around §3, §9, and §10.5/10.7 competency/proficiency definitions acknowledge measurement without operationalizing it. | Measurement complexity | P39: Pass 1 | Q39: Yes | U39: in
A40: 37 | B40: 34 | C40: SWGDE Training Guidelines for Video/Image Analysis and Photography | D40: 2019 | E40: SWGDE | F40: Training Guidelines | G40: Full document | H40: §9 Training Evaluation & Documentation | I40: "A means of testing an individual's competency…ongoing proficiency…a schedule for the completion of testing" | J40: TEC-01 | K40: — | L40: CRS-02 | N40: Document-level pattern: ORG-01 (scope exclusion) + TEC-01 (measurement complexity) are co-dominant. TEC-02 present at §5. PRO-01 confirmed via revision history. No AI-specific content (publication date 2016). CRS-02 flags cluster around §3, §9, and §10.5/10.7 competency/proficiency definitions acknowledge measurement without operationalizing it. | Measurement complexity | [code_3]: Competency testing mandated as process requirement no threshold, rubric, or quantitative standard | P40: Pass 1 | Q40: Yes | U40: in
A41: 38 | B41: 34 | C41: SWGDE Training Guidelines for Video/Image Analysis and Photography | D41: 2019 | E41: SWGDE | F41: Training Guidelines | G41: Full document | H41: §5 Introduction | I41: "Training should include only the use of validated technologies and methods…methods used for validating technologies" | J41: TEC-02 | K41: — | L41: — | N41: Document-level pattern: ORG-01 (scope exclusion) + TEC-01 (measurement complexity) are co-dominant. TEC-02 present at §5. PRO-01 confirmed via revision history. No AI-specific content (publication date 2016). CRS-02 flags cluster around §3, §9, and §10.5/10.7 competency/proficiency definitions acknowledge measurement without operationalizing it. | Validation methodology gap | P41: Pass 1 | Q41: Yes | U41: in
A42: 39 | B42: 34 | C42: SWGDE Training Guidelines for Video/Image Analysis and Photography | D42: 2019 | E42: SWGDE | F42: Training Guidelines | G42: Full document | H42: §10.5.1.8 §10.7.1.9 | I42: "Human factors relating to forming conclusions in analysis (e.g. bias)" [Video Analyst and Image Analyst training topics] | J42: TEC-01 | K42: — | L42: CRS-02 | N42: Document-level pattern: ORG-01 (scope exclusion) + TEC-01 (measurement complexity) are co-dominant. TEC-02 present at §5. PRO-01 confirmed via revision history. No AI-specific content (publication date 2016). CRS-02 flags cluster around §3, §9, and §10.5/10.7 competency/proficiency definitions acknowledge measurement without operationalizing it. | Measurement complexity | [code_3]: Bias acknowledged no protocol for detecting, quantifying, or correcting; no confidence adjustment mechanism | P42: Pass 1 | Q42: Yes | U42: in
A43: 40 | B43: 34 | C43: SWGDE Training Guidelines for Video/Image Analysis and Photography | D43: 2019 | E43: SWGDE | F43: Training Guidelines | G43: Full document | H43: §History (p. 14) | I43: Draft → Public Comment (Jun 2015) → Reworked (Sep 2015) → Re-released → Approved Jan 2016 → Final Feb 2016. Zero confidence content added across all cycles. | J43: PRO-01 | K43: — | L43: — | N43: Document-level pattern: ORG-01 (scope exclusion) + TEC-01 (measurement complexity) are co-dominant. TEC-02 present at §5. PRO-01 confirmed via revision history. No AI-specific content (publication date 2016). CRS-02 flags cluster around §3, §9, and §10.5/10.7 competency/proficiency definitions acknowledge measurement without operationalizing it. | Comment period friction | P43: Pass 1 | Q43: Yes | U43: in
A44: 63 | B44: 6 | C44: NIST SP 800-53 Rev 5 — Security and Privacy Controls for Information Systems and Organizations | D44: 2022 | E44: NIST SP 800 | F44: Special Publication (Final) | G44: Large document (~492 pages). AI-, confidence-, and validation-relevant sections. | H44: §1.1 Purpose and Applicability | I44: The use of these controls is mandatory for federal information systems in accordance with Office of Management and Budget (OMB) Circular A-130 and the provisions of the Federal Information Security Modernization Act [FISMA]…other organizations such as state, local, and tribal governments as well as private sector organizations are encouraged to consider using these guidelines, as appropriate. | J44: ORG-01 | N44: Mirrors the voluntary-framing ORG-01 found at Doc #3 (NIST AI 600-1) but with an inverted structure here mandatory for federal, voluntary for everyone else. This organizational scope bifurcation is a novel ORG-01 expression not yet seen in corpus. | P44: Pass 1 | Q44: No — codebook-constitutive (see Decision Log 4/18/2026) | U44: codebook_constitutive | V44: codebook-constitutive per Decision Log 2026-04-18
A45: 64 | B45: 6 | C45: NIST SP 800-53 Rev 5 — Security and Privacy Controls for Information Systems and Organizations | D45: 2022 | E45: NIST SP 800 | F45: Special Publication (Final) | G45: Large document (~492 pages). AI-, confidence-, and validation-relevant sections. | H45: §1.5 Revisions and Extensions | I45: The security and privacy controls in the control catalog are also expected to change over time as controls are withdrawn, revised, and added…the need for stability is addressed by requiring that proposed modifications to security and privacy controls go through a rigorous and transparent public review process to obtain public and private sector feedback. | J45: PRO-01 | K45: ORG-05 | N45: PRO-01 is most important here the stated design goal of stability over responsiveness is an institutional acknowledgment that the standard will lag emergent threats. | P45: Pass 1 | Q45: No — codebook-constitutive (see Decision Log 4/18/2026) | U45: codebook_constitutive | V45: codebook-constitutive per Decision Log 2026-04-18
A46: 65 | B46: 6 | C46: NIST SP 800-53 Rev 5 — Security and Privacy Controls for Information Systems and Organizations | D46: 2022 | E46: NIST SP 800 | F46: Special Publication (Final) | G46: Large document (~492 pages). AI-, confidence-, and validation-relevant sections. | H46: §2.5 Trustworthiness and Assurance | I46: Assurance is the measure of confidence that the system functionality is implemented correctly, operating as intended, and producing the desired outcome with respect to meeting the security and privacy requirements…Effective measures of trustworthiness are meaningful only to the extent that the requirements are complete, well-defined, and can be accurately assessed. | J46: TEC-01 | K46: CRS-02 | N46: The assurance definition is analytically significant NIST is working with a confidence-adjacent concept at the foundational level, establishing that such measurement is necessary, but the operational content to fulfill the definition is absent from this document and deferred to SP 800-53A. | P46: Pass 1 | Q46: No — codebook-constitutive (see Decision Log 4/18/2026) | U46: codebook_constitutive | V46: codebook-constitutive per Decision Log 2026-04-18
A47: 66 | B47: 6 | C47: NIST SP 800-53 Rev 5 — Security and Privacy Controls for Information Systems and Organizations | D47: 2022 | E47: NIST SP 800 | F47: Special Publication (Final) | G47: Large document (~492 pages). AI-, confidence-, and validation-relevant sections. | H47: §2.5, Evidence of Control Implementation callout | I47: During control selection and implementation, it is important for organizations to consider the evidence (e.g., artifacts, documentation) that will be needed to support current and future control assessments. Such assessments help determine whether the controls are implemented correctly, operating as intended, and satisfying security and privacy policies. | J47: TEC-02 | N47: This passage describes the need for evidence without describing its form. For traditional security controls, the gap may be filled by SP 800-53A. For AI-specific controls, no equivalent assessment guidance exists within this document family the gap is structural. | P47: Pass 1 | Q47: No — codebook-constitutive (see Decision Log 4/18/2026) | U47: codebook_constitutive | V47: codebook-constitutive per Decision Log 2026-04-18
A48: 67 | B48: 6 | C48: NIST SP 800-53 Rev 5 — Security and Privacy Controls for Information Systems and Organizations | D48: 2022 | E48: NIST SP 800 | F48: Special Publication (Final) | G48: Large document (~492 pages). AI-, confidence-, and validation-relevant sections. | H48: Chapter 3 Preface / Technology-Neutral Design Statement | I48: With few exceptions, the security and privacy controls in the catalog are policy-, technology-, and sector-neutral, meaning that the controls focus on the fundamental measures necessary to protect information and the privacy of individuals across the information life cycle. | J48: ORG-01 | K48: TEC-02 | M48: CRS-01 | N48: Technology neutrality as a principle excludes the AI-specific validation guidance that forensic practitioners require. This is the most explicit statement in the corpus of an institutional design choice that produces the AIDFIR gap. | P48: Pass 1 | Q48: No — codebook-constitutive (see Decision Log 4/18/2026) | U48: codebook_constitutive | V48: codebook-constitutive per Decision Log 2026-04-18
A49: 68 | B49: 6 | C49: NIST SP 800-53 Rev 5 — Security and Privacy Controls for Information Systems and Organizations | D49: 2022 | E49: NIST SP 800 | F49: Special Publication (Final) | G49: Large document (~492 pages). AI-, confidence-, and validation-relevant sections. | H49: RA-3(4) Predictive Cyber Analytics | I49: Advanced automation and analytics capabilities are typically supported by artificial intelligence concepts, including machine learning…Note, however, that sophisticated adversaries may be able to extract information related to analytic parameters and retrain the machine learning to classify malicious activity as benign. Accordingly, machine learning is augmented by human monitoring to ensure that sophisticated adversaries are not able to conceal their activities. | J49: TEC-01 | K49: TEC-06 | M49: CRS-01 | N49: AI capability is acknowledged, adversarial risk is noted, and the prescribed response is human augmentation rather than AI validation protocol. First and only AI-specific control enhancement in the document. | P49: Pass 1 | Q49: No — codebook-constitutive (see Decision Log 4/18/2026) | U49: codebook_constitutive | V49: codebook-constitutive per Decision Log 2026-04-18
A50: 69 | B50: 6 | C50: NIST SP 800-53 Rev 5 — Security and Privacy Controls for Information Systems and Organizations | D50: 2022 | E50: NIST SP 800 | F50: Special Publication (Final) | G50: Large document (~492 pages). AI-, confidence-, and validation-relevant sections. | H50: SI-3 Malicious Code Protection Discussion | I50: Nonsignature-based detection mechanisms include artificial intelligence techniques that use heuristics to detect, analyze, and describe the characteristics or behavior of malicious code and to provide controls against such code for which signatures do not yet exist or for which existing signatures may not be effective. | J50: TEC-02 | M50: CRS-02 | N50: An AI-based malicious code detection control that produces no guidance on how to validate its outputs, assess its false positive rate, or express confidence in its determinations is the operational embodiment of the AIDFIR gap. | P50: Pass 1 | Q50: No — codebook-constitutive (see Decision Log 4/18/2026) | U50: codebook_constitutive | V50: codebook-constitutive per Decision Log 2026-04-18
A51: 70 | B51: 6 | C51: NIST SP 800-53 Rev 5 — Security and Privacy Controls for Information Systems and Organizations | D51: 2022 | E51: NIST SP 800 | F51: Special Publication (Final) | G51: Large document (~492 pages). AI-, confidence-, and validation-relevant sections. | H51: SI-19(7) De-identification Validated Algorithms and Software | I51: Perform de-identification using validated algorithms and software that is validated to implement the algorithms. Algorithms that appear to remove personally identifiable information from a dataset may in fact leave information that is personally identifiable or data that is re-identifiable. | J51: TEC-02 | M51: CRS-02 | N51: Validation is required but not defined. The requirement is present; the standard to fulfill it is absent. Mirrors SWGDE's "validated technologies" language at the federal level. | P51: Pass 1 | Q51: No — codebook-constitutive (see Decision Log 4/18/2026) | U51: codebook_constitutive | V51: codebook-constitutive per Decision Log 2026-04-18
A52: 71 | B52: 6 | C52: NIST SP 800-53 Rev 5 — Security and Privacy Controls for Information Systems and Organizations | D52: 2022 | E52: NIST SP 800 | F52: Special Publication (Final) | G52: Large document (~492 pages). AI-, confidence-, and validation-relevant sections. | H52: Errata Table | I52: 12-10-2020 | Editorial | [18 distinct control-level corrections listed]…Zero confidence measurement or AI-specific guidance additions across all errata. | J52: PRO-01 | N52: One revision cycle, editorial only. No content addressing the measurement gaps identified elsewhere in the document. | P52: Pass 1 | Q52: No — codebook-constitutive (see Decision Log 4/18/2026) | U52: codebook_constitutive | V52: codebook-constitutive per Decision Log 2026-04-18
A53: 72 | B53: 10 | C53: NIST AI 100-2 (Adversarial ML) Draft to Final Comment Disposition | D53: 2024 | E53: NIST AI | F53: Comment Disposition Report | G53: Full document | H53: Background / Footnote 1, p.viii | I53: While practical guidance published by NIST may serve as an informative reference, this guidance remains voluntary. The content of this document reflects recommended practices. This document is not intended to serve as or supersede existing regulations, laws, or other mandatory guidance. | J53: ORG-01 | N53: Scope exclusion / voluntary framing. The identical voluntary disclaimer as Doc #3 and Doc #6. Third consecutive NIST AI document to open with explicit non-binding, non-regulatory disclaimer. NIST AI documents are structurally prohibited from prescribing mandatory validation standards for forensic use.
A54: 73 | B54: 10 | C54: NIST AI 100-2 (Adversarial ML) Draft to Final Comment Disposition | D54: 2024 | E54: NIST AI | F54: Comment Disposition Report | G54: Full document | H54: Executive Summary, p.xii | I54: This report does not make recommendations on risk tolerance (i.e., the level of risk that is acceptable to organizations or society) because it is highly contextual and specific to applications and use cases. | J54: ORG-01 | K54: TEC-01 | M54: CRS-02 | N54: Scope exclusion by deliberate design | O54: Measurement complexity | P54: Pass 1 | R54: Most analytically significant ORG-01 instance in the corpus. NIST names risk tolerance and declines to answer it. Institutional face of the AIDFIR gap.
A55: 74 | B55: 10 | C55: NIST AI 100-2 (Adversarial ML) Draft to Final Comment Disposition | D55: 2024 | E55: NIST AI | F55: Comment Disposition Report | G55: Full document | H55: §1 Introduction, p.2 | I55: Modern cryptography often relies on algorithms that are secure in an information-theoretic sense... there are no information-theoretic security proofs for the widely used ML algorithms in modern AI systems. | J55: TEC-01 | K55: TEC-04 | L55: CRS-01 | N55: Measurement complexity | O55: Insufficient empirical evidence base | P55: Pass 1 | R55: Establishes theoretical foundation for TEC-01 pattern. AI measurement science is immature, now at the mathematical level. AI-specific confidence gap directly and technically named
A56: 75 | B56: 10 | C56: NIST AI 100-2 (Adversarial ML) Draft to Final Comment Disposition | D56: 2024 | E56: NIST AI | F56: Comment Disposition Report | G56: Full document | H56: §4.1.1, p.55 | I56: AI systems that are optimized for accuracy alone tend to underperform in terms of adversarial robustness and fairness... it may not be possible to simultaneously maximize the performance of an AI system with respect to these attributes. | J56: TEC-01 | K56: TEC-06 | L56: CRS-01 | N56: Measurement complexity | O56: AI opacity / explainability barrier | R56: Pareto front argument applied to AIDFIR: confidence measurement for forensic AI tools cannot be reduced to a single dimension. Multi-dimensional AI performance trade-off confirmed as a structural barrier to single-metric confidence standards
A57: 76 | B57: 10 | C57: NIST AI 100-2 (Adversarial ML) Draft to Final Comment Disposition | D57: 2024 | E57: NIST AI | F57: Comment Disposition Report | G57: Full document | H57: §4.1.2, p.56 | I57: Designing mitigations is an inherently ad hoc and fallible process…An ongoing challenge in AML is the ability to detect when a model is under attack. | J57: TEC-02 | K57: TEC-06 | L57: CRS-01 | N57: Validation methodology gap | O57: AI opacity / explainability barrier | R57: "Ad hoc and fallible" characterization of mitigation design is the most direct NIST statement in the corpus that AI validation methodology is not merely incomplete but structurally limited. Fundamental limitation on AI reliability validation explicitly stated by NIST
A58: 77 | B58: 10 | C58: NIST AI 100-2 (Adversarial ML) Draft to Final Comment Disposition | D58: 2024 | E58: NIST AI | F58: Comment Disposition Report | G58: Full document | H58: §4.1.3, p.57 | I58: Another general problem of AML mitigations... is the lack of reliable benchmarks, which causes results from AML papers to be routinely incomparable... | J58: TEC-04 | K58: PRO-04 | L58: CRS-01 | N58: Insufficient empirical evidence base | O58: Deferred to future cycle | R58: NIST AI's own technical report states that AI mitigation results are routinely incomparable empirical foundation for prescriptive AI confidence standard does not currently exist. Benchmark incomparability confirmed as a structural barrier to AI confidence standardization
A59: 78 | B59: 10 | C59: NIST AI 100-2 (Adversarial ML) Draft to Final Comment Disposition | D59: 2024 | E59: NIST AI | F59: Comment Disposition Report | G59: Full document | H59: §4.2.5, p.59 | I59: A persistent challenge remains in the fact that many AML mitigations are empirical in nature and lack theoretical or provable guarantees... organizations seeking to manage risks... may need to consider practices and measures beyond adversarial testing. | J59: TEC-01 | K59: TEC-02 | L59: CRS-02 | N59: Measurement complexity | O59: Validation methodology gap | R59: NIST identifies "delegation of trust to models in high stakes contexts" as requiring measures beyond existing adversarial testing, then does not specify those measures. Validation requirement for high-stakes AI acknowledged, prescriptive protocol absent
A60: 79 | B60: 10 | C60: NIST AI 100-2 (Adversarial ML) Draft to Final Comment Disposition | D60: 2024 | E60: NIST AI | F60: Comment Disposition Report | G60: Full document | H60: §4.2.6, p.60 | I60: More precisely relating AML attacks and mitigations to processes for achieving these goals and managing risks in AI systems is an area for ongoing work. | J60: PRO-04 | N60: Deferred to future cycle | R60: Integration of AML security with AI risk management processes is explicitly characterized as ongoing future work.
A61: 80 | B61: 10 | C61: NIST AI 100-2 (Adversarial ML) Draft to Final Comment Disposition | D61: 2024 | E61: NIST AI | F61: Comment Disposition Report | G61: Full document | H61: Publication History, p.iv | I61: Approved by the NIST Editorial Review Board on 2025-03-20. | J61: PRO-01 | N61: Consultation process inadequacy | R61: Revision cycle produced expanded taxonomy and terminology but zero prescriptive confidence measurement protocols, error rate thresholds, or forensic-specific AI validation guidance.
A62: 81 | B62: 4 | C62: NIST CSF 2.0 — Public Comment Analysis Report | D62: 2024 | E62: NIST CSF | F62: News Release / Development Process Surrogate | G62: Full document | H62: Lede bullets, p.1 | I62: The update is the outcome of a multiyear process of discussions and public comments aimed at making the framework more effective | J62: ORG-01 | K62: PRO-03 | N62: Multiyear development process reflects organizational scope/capacity constraints on update frequency (ORG-01); formal public comment process confirms Tier 3-level procedural rigor (PRO-03) | P62: Pass 1 | R62: Saturation tracker: Log 0 new codes for Doc #4. All six codes (ORG-01, ORG-02, ORG-03, CRS-01, PRO-03, PRO-06) were existing codebook entries at time of coding.
A63: 82 | B63: 4 | C63: NIST CSF 2.0 — Public Comment Analysis Report | D63: 2024 | E63: NIST CSF | F63: News Release / Development Process Surrogate | G63: Full document | H63: Governance emphasis, pp. 1–2 | I63: Added emphasis on governance as well as supply chains; new Govern function added | J63: ORG-03 | N63: Organizational decision to elevate governance as a new function signals internal recognition that prior versions under-addressed accountability structures &mdash; ORG barrier acknowledged and acted upon | P63: Pass 1 | R63: Saturation tracker: Log 0 new codes for Doc #4. All six codes (ORG-01, ORG-02, ORG-03, CRS-01, PRO-03, PRO-06) were existing codebook entries at time of coding.
A64: 83 | B64: 4 | C64: NIST CSF 2.0 — Public Comment Analysis Report | D64: 2024 | E64: NIST CSF | F64: News Release / Development Process Surrogate | G64: Full document | H64: Resource ecosystem, p.4 (road graphic) | I64: Suite of supplementary resources: Implementation Examples, Quick Start Guides, Mappings, Reference Tool | J64: CRS-01 | K64: PRO-06 | M64: CRS-01 | N64: NIST deliberately structures CSF as a hub routing users outward for implementation specifics &mdash; no self-contained technical guidance (CRS-01); Reference Tool and mappings represent cross-document coordination infrastructure (PRO-06) | P64: Pass 1 | R64: Saturation tracker: Log 0 new codes for Doc #4. All six codes (ORG-01, ORG-02, ORG-03, CRS-01, PRO-03, PRO-06) were existing codebook entries at time of coding.
A65: 84 | B65: 4 | C65: NIST CSF 2.0 — Public Comment Analysis Report | D65: 2024 | E65: NIST CSF | F65: News Release / Development Process Surrogate | G65: Full document | H65: Scope expansion, p.1 | I65: CSF now explicitly aims to help all organizations &mdash; not just those in critical infrastructure &mdash; to manage and reduce risks | J65: ORG-02 | N65: Explicit organizational boundary expansion from critical infrastructure to all organizations is the structural mechanism that prevents prescriptive AI-specific guidance &mdash; consistent with CSWP 29 ORG-scope finding | P65: Pass 1 | R65: Saturation tracker: Log 0 new codes for Doc #4. All six codes (ORG-01, ORG-02, ORG-03, CRS-01, PRO-03, PRO-06) were existing codebook entries at time of coding.
A66: 85 | B66: 5 | C66: NIST IR 8354 (Digital Investigation Techniques) — Public Comment Period Record | D66: 2022 | E66: NIST CFTT | F66: Public Comment Record | G66: Full document | H66: §1.1 Scope, p.5 | I66: This report also does not address other issues such as improved methods for tool validation and verification, privacy, or legal issues, and managing forms of bias within forensic practice. These are outside the scope of this document. | J66: ORG-01 | K66: — | L66: — | M66: — | N66: Explicit scope exclusion of tool validation improvement, bias management, and legal issues — organizational boundary decision that structurally prevents the document from addressing AI-specific confidence and validation requirements. Fourth consecutive NIST document with this exclusion-by-scope framing. | P66: Pass 1
A67: 86 | B67: 5 | C67: NIST IR 8354 (Digital Investigation Techniques) — Public Comment Period Record | D67: 2023 | E67: NIST CFTT | F67: Public Comment Record | G67: Full document | H67: §2.8.5 Standards Organizations, p.25 | I67: ASTM E3016-18 Standard Guide for Establishing Confidence in Digital and Multimedia Evidence Forensic Results by Error Mitigation Analysis | J67: PRO-06 | K67: — | L67: — | M67: CRS-01 | N67: NIST IR 8354 references the ASTM E3016-18 confidence standard as an external document rather than incorporating its framework — confirms cross-document coordination architecture (PRO-06) and the hub-and-spoke pattern previously identified at CRS-01. This is the same ANSI/ASTM E3016-18 standard pending OSAC registry acceptance identified in entry 23. | P67: Pass 1
A68: 87 | B68: 5 | C68: NIST IR 8354 (Digital Investigation Techniques) — Public Comment Period Record | D68: 2024 | E68: NIST CFTT | F68: Public Comment Record | G68: Full document | H68: §4.7.1 Analysis Tools, p.39 | I68: AI tools are powerful, but not perfect, and should be used with caution due to unexpected behaviors. An AI tool may inadvertently introduce bias from a variety of sources. The tool outputs depend on the data set used to train the AI along with other factors and may not be relevant to the data at hand. Results could be misleading and should be verified or confirmed. | J68: TEC-01 | K68: TEC-06 | L68: — | M68: CRS-02 | N68: Measurement complexity — AI output validity is contingent on training data relevance, introducing non-quantifiable uncertainty (TEC-01); opacity/explainability barrier — tool behavior described as potentially unexpected with no prescribed mechanism for predicting or quantifying failure modes (TEC-06). CRS-02: verification mandated but no protocol specified for how to verify AI forensic tool outputs. | P68: Pass 1
A69: 88 | B69: 5 | C69: NIST IR 8354 (Digital Investigation Techniques) — Public Comment Period Record | D69: 2025 | E69: NIST CFTT | F69: Public Comment Record | G69: Full document | H69: §4.10.1 Error Rates, p.43 | I69: Digital processes tend to have systematic errors rather than random errors. Therefore, an error mitigation analysis provides more information and is the correct way to manage uncertainty. An error rate is only useful where there are random errors. | J69: TEC-01 | K69: — | L69: — | M69: CRS-02 | N69: NIST explicitly establishes that classical error rate metrics do not apply to digital forensic tools — the foundational measurement framework that confidence standards rely on is structurally inapplicable to this domain. Most direct statement in corpus of why AI-specific confidence measurement is a technically distinct problem. CRS-02: error mitigation analysis is recommended as the correct approach but no AI-specific protocol is specified. | P69: Pass 1
A70: 89 | B70: 5 | C70: NIST IR 8354 (Digital Investigation Techniques) — Public Comment Period Record | D70: 2026 | E70: NIST CFTT | F70: Public Comment Record | G70: Full document | H70: §4.10.3 Software Testing, p.45 | I70: There are no generally agreed requirements for each forensic task, i.e., no formal standard to test against. | J70: TEC-02 | K70: PRO-04 | L70: — | M70: — | N70: Validation methodology gap — absence of agreed requirements means no standard exists against which AI forensic tool outputs can be validated (TEC-02); deferred to future cycle — CFTT treats its own specifications as descriptive rather than prescriptive, meaning the gap is institutionally acknowledged but not scheduled for resolution (PRO-04). | P70: Pass 1
A71: 90 | B71: 5 | C71: NIST IR 8354 (Digital Investigation Techniques) — Public Comment Period Record | D71: 2027 | E71: NIST CFTT | F71: Public Comment Record | G71: Full document | H71: Chapter 5 Conclusions, p.52 | I71: While developing this report, we encountered many areas that need further research and improved processes, including better sharing of forensic knowledge... more efficient and consistent approaches to testing forensic tools... better sharing of forensic reference data... better analysis of how digital evidence is used and whether there have been incorrect or misleading conclusions. | J71: PRO-04 | K71: ORG-07 | L71: — | M71: — | N71: Deferred to future cycle — NIST explicitly enumerates multiple unresolved knowledge and process gaps and frames them as future research needs rather than active development commitments (PRO-04); no R&D needs escalation — the absence of a structured AI-specific research roadmap within NIST's own scientific foundation review mirrors the ORG-07 pattern previously identified in OSAC annual reports (ORG-07). | P71: Pass 1
A72: 91 | B72: 5 | C72: NIST IR 8354 (Digital Investigation Techniques) — Public Comment Period Record | D72: 2028 | E72: NIST CFTT | F72: Public Comment Record | G72: Full document | H72: §4.8 Verification and Validation, p.40 | I72: A software vendor is not required to disclose the software development process followed during tool development. | J72: ORG-02 | K72: — | L72: — | M72: — | N72: Resource/transparency constraint — absence of mandatory disclosure requirements means the evidentiary basis for AI tool confidence is structurally inaccessible to practitioners and standard-setters alike. Mirrors TEC-06 opacity pattern but at the organizational/regulatory level rather than the technical level. | P72: Pass 1 | R72: Doc #5 dominant pattern: TEC-01 and CRS-02 co-occur persistently throughout the error rate and tool testing sections. Key analytical finding — NIST's own scientific foundation review confirms that classical error rate metrics are structurally inapplicable to digital forensics (entry 88), which provides the strongest technical-foundation rationale in the corpus for why AI-specific confidence standards cannot simply adopt existing error rate frameworks. The ASTM E3016-18 cross-reference (entry 86) connects directly to the entry 23 OSAC registry stall finding. Together, entries 86 and 23 form a single barrier chain: the applicable confidence standard exists → is referenced by NIST → but remains outside the OSAC registry six-plus years after publication.
A73: 92 | B73: 7 | C73: NIST SP 800-61r3 (Incident Response) | D73: 2025 | E73: NIST SP 800 | F73: Public Comment Record [Proxy: Final Standard] | G73: Full document | H73: §1.1 Purpose and Scope, p.3 | I73: "Because the details of how to perform incident response activities change so often and vary so much across technologies, environments, and organizations, it is no longer feasible to capture and maintain that information in a single static publication." | J73: ORG-01 | K73: PRO-03 | N73: Scope exclusion — explicit institutional decision to retreat from prescriptive operational detail; the stated rationale (change velocity, environmental heterogeneity) mirrors ORG-01 scope exclusion logic in SWGDE documents but originates from organizational capacity reasoning rather than legal constraint | O73: Revision cycle omission — the shift from SP 800-61r2's operational detail to r3's high-level framework represents a deliberate removal of prescriptive content across revision cycles; this is PRO-03 in the direction of less specificity | P73: Pass 1 | Q73: No | R73: Structurally significant: this is the only corpus document where prescriptive content was removed in revision, rather than simply not added. SP 800-61r2 (2012) contained detailed incident handling procedures; r3 explicitly abandons that model. ORG-01 + PRO-03 co-occurrence here is the inverse of the typical pattern — most PRO-03 instances involve failure to add AI content; this instance involves deliberate subtraction of operational specificity. | U73: out
A74: 93 | B74: 7 | C74: NIST SP 800-61r3 (Incident Response) | D74: 2025 | E74: NIST SP 800 | F74: Public Comment Record [Proxy: Final Standard] | G74: Full document | H74: §1.1 Purpose and Scope, p.3 | I74: "Readers are encouraged to utilize other NIST resources in conjunction with this document…mappings to additional sources of information…available through the NIST Cybersecurity and Privacy Reference Tool (CPRT)." | J74: CRS-01 | K74: PRO-06 | M74: CRS-01 | N74: Hub-and-spoke architecture — document explicitly routes users outward to CPRT, CSF 2.0, and supplemental resources for implementation specifics; no self-contained technical guidance provided | O74: Standards coordination failure — operational detail is distributed across an ecosystem of linked documents (CSF 2.0, SP 800-53, CPRT mappings) with no single authoritative source for forensic AI validation; this is the same PRO-06 coordination architecture identified in Docs #4 and #5 | P74: Pass 1 | Q74: No | R74: Third consecutive NIST document using the CPRT/supplemental resources routing pattern as the primary implementation mechanism (Docs #4, #5, #7). This cross-document pattern strengthens the PRO-06 finding: the NIST SP 800 series structurally defers prescriptive content to a coordination ecosystem rather than embedding it. | U74: out
A75: 94 | B75: 7 | C75: NIST SP 800-61r3 (Incident Response) | D75: 2025 | E75: NIST SP 800 | F75: Public Comment Record [Proxy: Final Standard] | G75: Full document | H75: Table 3, DE.CM, p.23 | I75: "Tune the continuous monitoring technologies to reduce false positives and false negatives to acceptable levels." | J75: TEC-01 | M75: CRS-02 | N75: Measurement complexity — "acceptable levels" is undefined; the document acknowledges that a false positive/negative tolerance threshold should exist but provides no operationalization, no numeric range, and no method for determining what "acceptable" means in a given forensic context | P75: Pass 1 | Q75: No | R75: CRS-02 flag: non-prescriptive confidence language. The phrase "acceptable levels" appears in a High-priority subcategory recommendation but functions as a placeholder — it names the measurement requirement without providing the measurement standard. This is the only error-rate-adjacent language in the entire document. | U75: out
A76: 95 | B76: 7 | C76: NIST SP 800-61r3 (Incident Response) | D76: 2025 | E76: NIST SP 800 | F76: Public Comment Record [Proxy: Final Standard] | G76: Full document | H76: Table 2, GV.RM-03, p.12 | I76: "Have processes in place so that incident-related decision-making will be informed by other types of risks that the organization faces (e.g., privacy, operational, safety, reputational, AI) and not just cybersecurity risks in isolation." | J76: ORG-07 | M76: CRS-01 | N76: AI awareness gap — AI is listed parenthetically as one of five risk types without elaboration, dedicated guidance, or any downstream AI-specific recommendations anywhere in the document; a 2025 incident response publication that addresses AI only in a parenthetical list represents an unintentional absence relative to current operational context | P76: Pass 1 | Q76: No | R76: CRS-01 flag: AI mentioned without action. This is the sole AI reference in a 40-page 2025 federal incident response standard. The parenthetical placement alongside "reputational" risk signals that AI is recognized as a category but has not been integrated into the guidance architecture. Analytically this is the clearest ORG-07 instance in the NIST SP 800 series — the document clearly implicates AI incident contexts (ransomware, deepfakes, automated attack tools) yet AI validation guidance is absent apparently unintentionally. | U76: out
A77: 96 | B77: 7 | C77: NIST SP 800-61r3 (Incident Response) | D77: 2025 | E77: NIST SP 800 | F77: Public Comment Record [Proxy: Final Standard] | G77: Full document | H77: Table 3, RS.AN-07, p.29 | I77: "Formal evidence gathering and handling using chain-of-custody procedures might not be performed for every incident that occurs (e.g., most malware incidents will not result in prosecution). However, collected incident data is still considered evidence." | J77: TEC-02 | K77: ORG-06 | M77: CRS-02 | N77: Validation methodology gap — chain-of-custody as the operative evidence integrity mechanism is acknowledged as optional, yet no alternative validation framework is specified for incidents where formal procedures are not followed; the document leaves a methodological void at the point where AI-generated evidence would require the most rigorous handling | O77: Legal/admissibility concern — the explicit connection between evidence handling and prosecution potential reflects ORG-06 legal constraint logic; prescriptive chain-of-custody requirements are softened precisely because of litigation variability | P77: Pass 1 | Q77: No | R77: TEC-02 + ORG-06 co-occurrence mirrors the pattern first seen in Doc #42 (cloud acquisition) where legal variability prevents prescriptive procedural standardization. For AI forensic evidence specifically, the absence of a mandatory chain-of-custody protocol is analytically significant — AI output provenance (model version, training data, inference parameters) requires documentation beyond traditional chain-of-custody and no guidance exists for it here. | U77: out
A78: 97 | B78: 7 | C78: NIST SP 800-61r3 (Incident Response) | D78: 2025 | E78: NIST SP 800 | F78: Public Comment Record [Proxy: Final Standard] | G78: Full document | H78: Appendix C Change Log, p.40 | I78: "Performed a full rewrite of the previous content…Shifted the focus of the document from guidelines on detecting, analyzing, prioritizing, and handling incidents to recommendations and considerations for incorporating cybersecurity incident response considerations throughout an organization's cybersecurity risk management activities." | J78: PRO-03 | K78: ORG-01 | N78: Revision cycle omission — the change log confirms that the rewrite explicitly replaced operational detection and analysis guidelines with high-level risk management considerations; this is a documented, deliberate removal of the type of prescriptive content where AI validation guidance would reside | O78: Scope exclusion — the shift from operational guidelines to risk management considerations is an organizational scope decision, not merely a presentational one; it structurally removes the document as a vehicle for AI-specific forensic validation guidance | P78: Pass 1 | Q78: No | R78: The Change Log is the most analytically valuable section for Phase 2 purposes: it provides an authoritative institutional record that prescriptive operational content was intentionally removed. This directly supports the dissertation argument that the AIDFIR gap in NIST SP 800-series documents is structural — the 2025 revision moved away from, not toward, the kind of operational specificity that AI validation guidance requires. Strongest PRO-03 instance in the NIST SP 800 sub-corpus. | U78: out
A79: 98 | B79: 20 | C79: NIST SP 800-218A (Secure Dev for GenAI) | D79: 2024 | E79: NIST SP 800 | F79: Public Comment Record [Proxy: Final Standard] | G79: Full document | H79: §1.2 Scope, p.2 | I79: "Consistent with SSDF version 1.1 and EO 14110, practices for the deployment and operation of AI systems with AI models are out of scope." | J79: ORG-01 | N79: Scope exclusion — the explicit exclusion of AI deployment and operation from scope is the single most analytically significant feature of this document for AIDFIR purposes; forensic AI tool validation occurs at deployment and operation, not at development; this scope decision structurally prevents the document from addressing the AIDFIR gap regardless of its AI-specific content | P79: Pass 1 | Q79: No | R79: This is the most precisely targeted ORG-01 in the corpus. Unlike previous ORG-01 instances (which exclude AI generally), this one excludes specifically the deployment/operation lifecycle stage — the exact stage where forensic practitioners would need confidence and validation guidance. The document is rich with AI-specific development guidance yet structurally unable to address the AIDFIR gap by design. | U79: out
A80: 99 | B80: 20 | C80: NIST SP 800-218A (Secure Dev for GenAI) | D80: 2024 | E80: NIST SP 800 | F80: Public Comment Record [Proxy: Final Standard] | G80: Full document | H80: §1.1 Purpose / Authority, p.iii | I80: "This publication may be used by nongovernmental organizations on a voluntary basis and is not subject to copyright in the United States." | J80: ORG-01 | N80: Scope exclusion / voluntary framing — fourth consecutive NIST document with the identical voluntary disclaimer; confirms structural pattern that NIST AI documents cannot prescribe mandatory validation standards | P80: Pass 1 | Q80: No | R80: Saturation confirmed on voluntary framing ORG-01. No new analytical content — pattern is fully established across Docs #3, #6, #7, #10, #20. | U80: out
A81: 100 | B81: 20 | C81: NIST SP 800-218A (Secure Dev for GenAI) | D81: 2024 | E81: NIST SP 800 | F81: Public Comment Record [Proxy: Final Standard] | G81: Full document | H81: §2 Using the SSDF Community Profile, p.4 | I81: "AI model and system development is still much more of an art than an exact science, requiring developers to interact with model code, training data, and other parameters over multiple iterations." | J81: TEC-01 | M81: CRS-02 | N81: Measurement complexity — NIST explicitly characterizes AI development as non-scientific and iterative, directly undermining the possibility of standardized confidence measurement; this is the strongest TEC-01 framing in the corpus because it comes from a document dedicated to AI development guidance | P81: Pass 1 | Q81: No | R81: CRS-02 flag: non-prescriptive confidence language. "Art than an exact science" is the most direct NIST statement in the corpus of the epistemic problem underlying TEC-01. Pairs with Doc #10 entry 76 ("inherently ad hoc and fallible"). Together these two passages constitute NIST's official acknowledgment that AI measurement science is not yet mature enough for prescriptive standards. | U81: out
A82: 101 | B82: 20 | C82: NIST SP 800-218A (Secure Dev for GenAI) | D82: 2024 | E82: NIST SP 800 | F82: Public Comment Record [Proxy: Final Standard] | G82: Full document | H82: §2, p.4 | I82: "Generative AI and dual-use foundation models present additional challenges in tracking model versioning and lineage…the final model weights are defined only after the model is trained and fine-tuned; this is where limitations in tracking all aspects of collection, processing, and training arise." | J82: TEC-02 | K82: TEC-06 | M82: CRS-02 | N82: Validation methodology gap — the provenance tracking problem for model weights is explicitly acknowledged as a structural limitation of current methodology; even with full compliance, the document cannot guarantee complete validation of AI model lineage | O82: AI opacity/explainability barrier — model weights as the core determinant of AI output are explicitly identified as opaque to full tracking; this is TEC-06 at the development level, confirming that opacity is structural not incidental | P82: Pass 1 | Q82: No | R82: This is the development-side expression of the same opacity barrier identified at the operational level in Doc #39 (§7.4.3) and Doc #10. The weight-opacity problem means that even a perfectly documented AI forensic tool cannot provide full provenance for its outputs — the validation gap is baked in at the architecture level. | U82: out
A83: 102 | B83: 20 | C83: NIST SP 800-218A (Secure Dev for GenAI) | D83: 2024 | E83: NIST SP 800 | F83: Public Comment Record [Proxy: Final Standard] | G83: Full document | H83: §2, p.5 | I83: "A limitation of the SSDF and this Profile is that they only address cybersecurity risk management. There are many other types of risks to AI systems (e.g., data privacy, intellectual property, and bias) that organizations should manage along with cybersecurity risk." | J83: ORG-01 | K83: PRO-06 | N83: Scope exclusion — bias, data privacy, and non-security AI risks are explicitly out of scope; for forensic AI validation, bias quantification and output reliability are central concerns, not peripheral ones; the scope exclusion directly prevents the document from addressing AIDFIR-relevant dimensions | O83: Standards coordination failure — the document routes bias, fairness, and broader AI risk to the AI RMF, NIST SP 1270, and other documents; no single document addresses the full validation picture; the hub-and-spoke PRO-06 pattern confirmed for the fifth consecutive NIST document | P83: Pass 1 | Q83: No | R83: ORG-01 + PRO-06 co-occurrence mirrors Docs #4, #5, #7. The scope limitation here is particularly sharp: bias is a critical forensic AI concern (false identification rates differ across demographic groups) yet it is explicitly sent to a different document. The coordination chain is: bias → AI RMF → NIST SP 1270 → no forensic-specific operationalization anywhere in the chain. | U83: out
A84: 103 | B84: 20 | C84: NIST SP 800-218A (Secure Dev for GenAI) | D84: 2024 | E84: NIST SP 800 | F84: Public Comment Record [Proxy: Final Standard] | G84: Full document | H84: Table 1, PO.3.3, p.10 | I84: "An artifact is 'a piece of evidence'…Evidence is 'grounds for belief or disbelief; data on which to base proof or to establish truth or falsehood'…Examples of artifacts specific to AI model development include attestations of the integrity and provenance of training datasets." | J84: TEC-02 | M84: CRS-02 | N84: Validation methodology gap — the document adopts a legal/evidentiary definition of evidence and applies it to AI model artifacts, then defines the artifacts as attestations of provenance rather than validated output confidence; the gap between evidence-of-process and evidence-of-output-validity is the core AIDFIR problem, and this passage sits precisely at that boundary without crossing it | P84: Pass 1 | Q84: No | R84: Most analytically rich single passage in the document. NIST uses the word "evidence" in both its legal/evidentiary sense and its technical sense simultaneously — then the only example given is dataset provenance attestation, not output confidence. This is the AIDFIR gap expressed in miniature: the evidence infrastructure exists for development provenance, but nothing equivalent exists for operational output validity. | U84: out
A85: 104 | B85: 13 | C85: NIST IR 8596 iprd (Cyber AI Profile) | D85: 2025 | E85: NIST AI | F85: Working Group Notes / Workshop Summary | G85: Full document | H85: §1 Introduction, p.2 | I85: "The NIST Cybersecurity Framework (CSF) 2.0 provides voluntary guidance to help organizations manage, reduce, and communicate cybersecurity risks." | J85: ORG-01 | N85: Scope exclusion / voluntary framing — fifth consecutive NIST document opening with the voluntary disclaimer; saturation on this pattern is confirmed | P85: Pass 1 | Q85: No | R85: Saturation fully confirmed on voluntary ORG-01. No new analytical content from this instance. Log for frequency count only. | U85: out
A86: 105 | B86: 13 | C86: NIST IR 8596 iprd (Cyber AI Profile) | D86: 2025 | E86: NIST AI | F86: Working Group Notes / Workshop Summary | G86: Full document | H86: §1 Introduction, p.2 | I86: "Per the AI Action Plan, the AI RMF is currently in revision and will be included in a future version." (footnote 5) | J86: PRO-04 | N86: Deferred to future cycle — the foundational AI risk framework that this Profile is explicitly built upon is itself under revision and not yet integrated; the Cyber AI Profile cannot reference a complete AI RMF because it does not yet exist in final form; AI governance infrastructure is incomplete at the time of this document's publication | P86: Pass 1 | Q86: No | R86: Analytically significant: the AI RMF revision footnote reveals that the NIST AI governance ecosystem is still under construction in 2025. The Profile references the AI RMF as a foundational resource (Introduction) while simultaneously acknowledging it is unavailable in final form. This is the clearest PRO-04 instance in the NIST AI sub-corpus — not a single document deferring content, but the entire AI risk management infrastructure being deferred. | U86: out
A87: 106 | B87: 13 | C87: NIST IR 8596 iprd (Cyber AI Profile) | D87: 2025 | E87: NIST AI | F87: Working Group Notes / Workshop Summary | G87: Full document | H87: Note to Reviewers / §2.3 Profile tables, p.15 | I87: "NOTE: Work remains ongoing to gather input and feedback, and significant changes are possible before finalizing the Cyber AI Profile. The Cyber AI Profile Preliminary Draft and the tables that follow are an early representation of work in progress." | J87: PRO-04 | K87: PRO-03 | N87: Deferred to future cycle — the entire document is explicitly characterized as incomplete work in progress; AI-specific cybersecurity guidance at the framework level does not yet exist in finalized form as of December 2025 | O87: Revision cycle omission — the preliminary draft status means all AI validation content present in this document may be removed, modified, or further generalized before publication; the document cannot be treated as a settled standard | P87: Pass 1 | Q87: No | R87: PRO-04 + PRO-03 co-occurrence is analytically novel — this is the only corpus document where both codes apply simultaneously to the document as a whole rather than to specific passages. The document is not just deferring specific content; its entire existence is preliminary. For dissertation purposes: the most recent NIST AI cybersecurity framework document as of late 2025 is still in preliminary draft, confirming that the institutional infrastructure for AI-specific cybersecurity validation guidance is actively under construction, not merely lagging. | U87: out
A88: 107 | B88: 13 | C88: NIST IR 8596 iprd (Cyber AI Profile) | D88: 2025 | E88: NIST AI | F88: Working Group Notes / Workshop Summary | G88: Full document | H88: §2.1.1 Securing AI System Components, p.9–10 | I88: "Compared to other types of computer systems, AI behavior and vulnerabilities tend to be more contextual, dynamic, opaque, and harder to predict, as well as more difficult to identify, verify, diagnose, and document, when they appear. Once issues are identified, they can also be difficult to mitigate as some vulnerabilities are inherent to the AI model or the underlying training data and machine-learning infrastructure." | J88: TEC-01 | K88: TEC-06 | M88: CRS-02 | N88: Measurement complexity — NIST formally characterizes AI as harder to identify, verify, diagnose, and document than other computer systems; this is a foundational statement that confidence measurement for AI is structurally more difficult, not just currently underdeveloped | O88: AI opacity/explainability barrier — "opaque," "harder to predict," and "inherent to the AI model or underlying training data" directly name the opacity/explainability barrier as a structural feature of AI systems, not a solvable technical problem | P88: Pass 1 | Q88: No | R88: CRS-02 flag: non-prescriptive confidence language. This is the most authoritative TEC-01 + TEC-06 co-occurrence in the corpus — a 2025 NIST preliminary standard explicitly and formally characterizing AI opacity and measurement difficulty as structural. Stronger than Doc #20's "art not science" framing because it comes from a document specifically focused on AI cybersecurity governance. Directly supports the theoretical grounding for the AIDFIR gap argument. | U88: out
A89: 108 | B89: 13 | C89: NIST IR 8596 iprd (Cyber AI Profile) | D89: 2025 | E89: NIST AI | F89: Working Group Notes / Workshop Summary | G89: Full document | H89: GV.RR-02 Defend Focus Area table | I89: "Safeguarding AI defense actions against adversarial manipulation, model drift, and hallucination with HITL checks and confidence thresholds that indicate whether an AI output is reliable enough to act upon." | J89: TEC-02 | M89: CRS-02 | N89: Validation methodology gap — confidence thresholds are named as the mechanism for determining AI output reliability, but no threshold values, derivation methods, or standardized confidence expression framework is provided; the gap between naming the solution and specifying it is exactly the AIDFIR gap | P89: Pass 1 | Q89: No | R89: CRS-02 flag: non-prescriptive confidence language. This is the most direct statement in the entire corpus that confidence thresholds for AI outputs are needed for operational decision-making — yet the threshold values and methodology remain unspecified. For the dissertation: this passage can serve as the primary exhibit of the AIDFIR gap as recognized by NIST itself — the need is named, the standard does not exist. | U89: out
A90: 109 | B90: 13 | C90: NIST IR 8596 iprd (Cyber AI Profile) | D90: 2025 | E90: NIST AI | F90: Working Group Notes / Workshop Summary | G90: Full document | H90: ID.IM-01 General Considerations table | I90: "AI introduces a suite of new metrics to consider. Carefully select which metrics closely align with the organization's goals. For instance, perhaps FPs are much more important than false negatives, in which case evaluation metrics will be more heavily influenced by precision rather than recall, and using metrics such as an F1 score may obfuscate results." | J90: TEC-01 | M90: CRS-02 | N90: Measurement complexity — NIST explicitly acknowledges that AI metric selection is context-dependent and that standard aggregate metrics (F1 score) may obfuscate rather than clarify AI performance; this is the corpus's clearest statement that AI error rate quantification cannot be reduced to a single universal standard — the measurement problem is irreducibly complex | P90: Pass 1 | Q90: No | R90: CRS-02 flag: non-prescriptive confidence language. The F1 obfuscation warning is analytically significant: it establishes that even when organizations want to quantify AI error rates, the choice of metric is itself contested and context-dependent. This directly explains why prescriptive error rate standards have not emerged — the measurement science is not settled. Connects to Doc #10 (Pareto front argument, entry 75) and Doc #5 (error rate inapplicability, entry 88) forming a three-document theoretical chain. | U90: out
A91: 110 | B91: 13 | C91: NIST IR 8596 iprd (Cyber AI Profile) | D91: 2025 | E91: NIST AI | F91: Working Group Notes / Workshop Summary | G91: Full document | H91: Training section, Defend table | I91: "AI-enabled defense actions, adversarial ML, prompt injection, model drift, and AI forensics to support personnel in building skills and knowledge." | J91: ORG-07 | M91: CRS-01 | N91: AI awareness gap — "AI forensics" is named as a training topic within a cybersecurity defense training recommendation but receives no further elaboration, no definition, and no associated guidance in any other section of the document; the term appears once and is not operationalized | P91: Pass 1 | Q91: No | R91: CRS-01 flag: AI mentioned without action. This is the only appearance of "AI forensics" in the entire corpus across all 13 coded documents. Its appearance as a single parenthetical training topic — with no associated standards, protocols, or guidance — is a precise encapsulation of the AIDFIR gap at the institutional level: the field of AI forensics is recognized as requiring specialized skills but no standards exist to define what those skills should produce or how outputs should be validated. | U91: out
A92: 111 | B92: 21 | C92: SWGDE Best Practices for Digital Forensic Video Analysis (18-V-001-2.0) — Revisi | D92: 2025 | E92: SWGDE Video | F92: Revision History (embedded) | G92: Revision history / change log section only (embedded in versioned PDF) | H92: §1 Introduction, p.2 | I92: "No warranty or other representation as to SWGDE work product is made or intended." (cover page) + "These guidelines may also be used to assist organizations when developing standard operating procedures (SOPs) for the processing of video evidence. Organizations should align to the best practices in this document to ensure they adhere to governmental and local laws, regulations, and SOPs." | J92: ORG-01 | K92: — | L92: — | M92: CRS-02 | N92: Scope exclusion / voluntary framing — SWGDE positions the document as best-practice guidance to assist SOP development, not as a prescriptive technical standard. The no-warranty disclaimer plus the "may be used to assist" framing is the SWGDE voluntary-alignment frame repeatedly observed across the sub-corpus. CRS-02 flags "should align" as non-prescriptive language.
A93: 112 | B93: 21 | C93: SWGDE Best Practices for Digital Forensic Video Analysis (18-V-001-2.0) — Revisi | D93: 2026 | E93: SWGDE Video | F93: Revision History (embedded) | G93: Revision history / change log section only (embedded in versioned PDF) | H93: §2 Limitations, p.2 | I93: "This document is not a training manual, nor a step-by-step methodology." | J93: ORG-01 | K93: — | L93: — | M93: — | N93: Scope exclusion — explicit self-limitation of the document's reach. The standard explicitly declines to provide methodology. This is a second ORG-01 signal distinct from entry 111 (warranty disclaimer); it operates at the scope-of-content level rather than the legal-framing level.
A94: 113 | B94: 21 | C94: SWGDE Best Practices for Digital Forensic Video Analysis (18-V-001-2.0) — Revisi | D94: 2027 | E94: SWGDE Video | F94: Revision History (embedded) | G94: Revision history / change log section only (embedded in versioned PDF) | H94: §3.2.1 Types of Examinations, p.3–4 | I94: Enumeration of 12 examination types (Metadata/Structural Analysis, Transcoding, Timeline Sequence Reconstruction, Speed/Motion Analysis, Pattern/Video Frame Info Analysis, Macroblock Analysis, Frame Difference, Video Frame Extraction, Video Clarification, Comparison, Video File Repair, Video Authentication, Video Recovery, Photogrammetric Analysis, Content Analysis). No examination type includes AI/ML-based analysis (e.g., AI-assisted object detection, facial recognition, deepfake detection, generative-AI authentication). | J94: ORG-07 | K94: — | L94: — | M94: — | N94: AI awareness gap — the December 2025 v2.0 revision exhaustively enumerates FVA examination types but does not include any AI/ML-based examination category. Given AI tools are routinely used in video clarification, object tracking, and deepfake detection, this is an absence where AI would be expected. Distinguished from ORG-01 (no explicit exclusion language) and PRO-04 (no deferral statement) — the absence is unintentional or unacknowledged.
A95: 114 | B95: 21 | C95: SWGDE Best Practices for Digital Forensic Video Analysis (18-V-001-2.0) — Revisi | D95: 2028 | E95: SWGDE Video | F95: Revision History (embedded) | G95: Revision history / change log section only (embedded in versioned PDF) | H95: §3.2.1 — Comparison bullet, p.4 | I95: "Comparison: The analysis of video to extract individual frames and prepare images for comparison. This type of examination can be applied to objects or persons for identification purposes. It requires proper training and a comparison methodology." | J95: TEC-02 | K95: — | L95: — | M95: CRS-02 | N95: Validation methodology gap — comparison for identification (including facial comparison) is recognized as requiring "proper training and a comparison methodology," but no validation protocol, error rate reporting requirement, or confidence framework is specified within this document (cross-references are made to 15-I-002-1.1 and 18-I-003-1.0). CRS-02 flags "proper training" as non-prescriptive.
A96: 115 | B96: 21 | C96: SWGDE Best Practices for Digital Forensic Video Analysis (18-V-001-2.0) — Revisi | D96: 2029 | E96: SWGDE Video | F96: Revision History (embedded) | G96: Revision history / change log section only (embedded in versioned PDF) | H96: §3.2.1 — Video Authentication bullet, p.4 | I96: "Video Authentication: An examination to determine if the file's video content, context, and structure align with the information provided about the file." | J96: PRO-06 | K96: — | L96: — | M96: CRS-01 | N96: Standards coordination failure (hub-and-spoke) — authentication is defined only by cross-reference to SWGDE 23-V-001-1.2. Given the 2024–2025 rise of generative-AI video (deepfakes), the authentication category is named but not operationalized within this document, relying entirely on an external document to carry any AI-relevant content. CRS-01 flags AI deepfake authentication as implicitly invoked but without explicit action.
A97: 116 | B97: 21 | C97: SWGDE Best Practices for Digital Forensic Video Analysis (18-V-001-2.0) — Revisi | D97: 2030 | E97: SWGDE Video | F97: Revision History (embedded) | G97: Revision history / change log section only (embedded in versioned PDF) | H97: §4.3.3 Processing, p.9 | I97: "Any processing performed on the video files should be completed on the working copy and sufficiently documented so that the methods can be reproduced and independently evaluated. This documentation should include the order and settings in which the processes were applied to ensure the integrity and the reproducibility of the results." | J97: TEC-01 | K97: — | L97: — | M97: CRS-02 | N97: Measurement complexity (reproducibility framing) — the document mandates reproducibility at the process-documentation level (comparably trained analyst test) but specifies no metric, threshold, or quantitative standard for measuring whether reproducibility has been achieved. This is SWGDE's characteristic pattern: reproducibility as process requirement rather than measurement standard. CRS-02 flags "sufficiently documented" and "ensure reproducibility" as non-prescriptive.
A98: 117 | B98: 21 | C98: SWGDE Best Practices for Digital Forensic Video Analysis (18-V-001-2.0) — Revisi | D98: 2031 | E98: SWGDE Video | F98: Revision History (embedded) | G98: Revision history / change log section only (embedded in versioned PDF) | H98: §4.3.4 Clarification, p.11 | I98: "Clarification techniques shall be documented in a manner to permit a comparably trained forensic analyst to understand the steps taken, the techniques used, and to extract comparable information from the processed file." | J98: TEC-01 | K98: — | L98: — | M98: CRS-02 | N98: Measurement complexity — "comparable information" is the reproducibility standard but is not operationalized. The "comparably trained analyst" test recurs across SWGDE documents as the reproducibility proxy. This is the same pattern as entry 116 but applied specifically to clarification. CRS-02 flag on "comparable information."
A99: 118 | B99: 21 | C99: SWGDE Best Practices for Digital Forensic Video Analysis (18-V-001-2.0) — Revisi | D99: 2032 | E99: SWGDE Video | F99: Revision History (embedded) | G99: Revision history / change log section only (embedded in versioned PDF) | H99: §4.4.1 Opinions, p.12 | I99: "In instances where a quantitative response is required, a margin of error may be expected, based on the frame information and compression of the images." | J99: TEC-01 | K99: — | L99: — | M99: CRS-02 | N99: Measurement complexity — the document acknowledges that quantitative FVA outputs carry margin of error but provides no methodology for computing, expressing, or reporting it. "May be expected" is explicitly non-prescriptive. This is the most direct error-quantification statement in the document and it is left fully open. CRS-02 flag.
A100: 119 | B100: 21 | C100: SWGDE Best Practices for Digital Forensic Video Analysis (18-V-001-2.0) — Revisi | D100: 2033 | E100: SWGDE Video | F100: Revision History (embedded) | G100: Revision history / change log section only (embedded in versioned PDF) | H100: §4.4.1 Opinions, p.12 | I100: "In instances where the opinion cannot definitively answer the question being asked, an answer of 'inconclusive' may be the only appropriate response." | J100: TEC-01 | K100: — | L100: — | M100: CRS-02 | N100: Measurement complexity — the document's confidence framework collapses to a binary (definitive vs. inconclusive) with no intermediate graded confidence expression. No calibration framework, no scaled reporting language, no quantified uncertainty. The "inconclusive" fallback is the de facto uncertainty expression mechanism. CRS-02 flag.
...

Sheet Document Tracker
A1: Phase 2 Document Tracker — Coding Progress by Document
A2: Update 'Status' and 'Passages coded' after each document. Flag κ subsample docs for Pass 2 scheduling.
A3: Doc # | B3: Title (short) | C3: Year | D3: Source | E3: Artifact type | F3: Coding unit | G3: κ subsample? | H3: Status | I3: Passages coded | J3: Memo written?
A4: 39 | B4: SWGDE Overview: Artificial Intelligence Trends in Video Analysis (v1.0) | C4: 2021 | D4: SWGDE Video | E4: Published Document (AI-specific) — PRIORITY | F4: Full document | G4: Yes | H4: Pass 1 complete | I4: 7 | J4: Yes
A5: 38 | B5: SWGDE Position on Facial Recognition and Facial Comparison — Development and Com | C5: 2022 | D5: SWGDE Imaging | E5: Position Document (published) | F5: Full document | G5: Yes | H5: Pass 1 complete | I5: 6 | J5: Yes
A6: C1 | B6: NIST OSAC FSSB Meeting Agendas — Public Sessions (2023, multiple quarters) | C6: 2023 | D6: NIST OSAC | E6: Meeting Agenda (Public) | F6: Full document | G6: Yes | H6: Pass 1 complete | I6: 5 | J6: Yes
A7: 1 | B7: NIST AI RMF Development — Public Comments Received During RFC Period | C7: 2023 | D7: NIST AI | E7: Public Comment Record | F7: Full document | G7: No | H7: Pass 1 complete | I7: 0 | J7: Yes
A8: 16 | B8: NIST OSAC Annual Reports — Digital/Multimedia SAC (2020, 2021, 2022, 2023) [cons | C8: 2020–2023 | D8: NIST OSAC | E8: Annual Report / Organizational Newsletter | F8: Full document | G8: Yes | H8: Pass 1 complete | I8: 6 | J8: Yes
A9: 2 | B9: NIST AI RMF Stakeholder Input Summary (Workshop Ancillary Documentation) | C9: 2023 | D9: NIST AI | E9: Public Comment Record | F9: Full document | G9: No | H9: Pass 1 complete | J9: No
A10: 3 | B10: NIST AI 600-1 (Generative AI) — Public Comment Summary | C10: 2024 | D10: NIST AI | E10: Public Comment Record | F10: Full document | G10: Yes | H10: Pass 1 complete | J10: No
A11: 4 | B11: NIST CSF 2.0 — Public Comment Analysis Report | C11: 2024 | D11: NIST CSF | E11: News Release / Development Process Surrogate, | F11: Full document | G11: Yes | H11: Pass 2 complete | I11: 7 | J11: Yes
A12: 5 | B12: NIST IR 8354 (Digital Investigation Techniques) — Public Comment Period Record | C12: 2022 | D12: NIST CFTT | E12: Public Comment Record | F12: Full document | G12: No | H12: Pass 1 complete | I12: 0 | J12: Yes
A13: 6 | B13: NIST SP 800-53 Rev 5 — Comment Disposition Report | C13: 2022 | D13: NIST SP 800 | E13: Comment Disposition Report | F13: AI- and confidence-relevant comment threads only (large-volume CDR — apply within-document sampling) | G13: Yes | H13: Pass 1 complete | I13: 9 | J13: Yes
A14: 7 | B14: NIST SP 800-61 Rev 3 (Incident Response) — Public Comment Record | C14: 2024 | D14: NIST SP 800 | E14: Public Comment Record | F14: Full document | G14: Yes | H14: Pass 1 complete | I14: 6 | J14: Yes
A15: 8 | B15: NIST SP 800-92 Rev 1 (Log Management) — Initial Public Draft Comment Summary | C15: 2023 | D15: NIST SP 800 | E15: Public Comment Record | F15: Full document | G15: No | H15: Pass 1 complete | J15: No
A16: 9 | B16: NIST CSF 2.0 — Change Log and Revision History (v1.1 to v2.0) | C16: 2024 | D16: NIST CSF | E16: Revision History | F16: Revision history / change log section only (embedded in versioned PDF) | G16: No | H16: Pass 1 complete | J16: No
A17: 10 | B17: NIST AI 100-2 (Adversarial ML) — Draft to Final Comment Disposition | C17: 2024 | D17: NIST AI | E17: Comment Disposition Report | F17: Full document | G17: Yes | H17: Pass 1 complete | J17: Yes
A18: 11 | B18: NIST CFTT Mobile Spec v3.1 — Change Summary from v3.0 | C18: 2021 | D18: NIST CFTT | E18: Revision History (embedded) | F18: Revision history / change log section only (embedded in versioned PDF) | G18: No | H18: Pass 1 complete | J18: No
A19: 12 | B19: NIST CFTT Mobile Spec v3.2 — Change Summary from v3.1 | C19: 2024 | D19: NIST CFTT | E19: Revision History (embedded) | F19: Revision history / change log section only (embedded in versioned PDF) | G19: No | H19: Pass 1 complete | J19: No
A20: 13 | B20: NIST IR 8596 (Cyber AI Profile) — Preliminary Draft Workshop Summary | C20: 2025 | D20: NIST AI | E20: Working Group Notes / Workshop Summary | F20: Full document | G20: Yes | H20: Pass 1 complete | I20: 0 | J20: No
A21: 14 | B21: NIST AI 100-4 (Synthetic Content) — Public Workshop and Stakeholder Feedback | C21: 2025 | D21: NIST AI | E21: Public Comment Record | F21: Full document | G21: Yes | H21: Pass 1 complete | J21: No
A22: 15 | B22: NIST OpenMFC 2020-2021 Evaluation Proceedings and Participant Feedback | C22: 2022 | D22: NIST AI | E22: Working Group Notes / Evaluation Proceedings | F22: Full document | G22: No | H22: Pass 1 complete | I22: 10 | J22: Yes | L22: Remaining work: Tier 1 κ documents #21, #25, #26, #28 only. Saturation sampling is complete.
A23: 20 | B23: NIST SP 800-218A (Secure Dev for GenAI) — Draft Comment Disposition | C23: 2025 | D23: NIST SP 800 | E23: Public Comment Record | F23: Full document | G23: No | H23: Pass 1 complete | I23: 0 | J23: No
A24: 21 | B24: SWGDE Best Practices for Digital Forensic Video Analysis (18-V-001-2.0) — Revisi | C24: 2025 | D24: SWGDE Video | E24: Revision History (embedded) | F24: Revision history / change log section only (embedded in versioned PDF) | G24: Yes | H24: Pass 2 complete | I24: 11 | J24: Yes
A25: 22 | B25: SWGDE Best Practices for Computer Forensic Examinations (18-F-001-2.0) — Comment | C25: 2025 | D25: SWGDE Forensics | E25: Revision History (embedded) | F25: Revision history / change log section only (embedded in versioned PDF) | G25: No | H25: Pass 1 complete | J25: No
A26: 23 | B26: SWGDE Legal and Scientific Support: Admissibility of Image Examinations (23-I-00 | C26: 2025 | D26: SWGDE Imaging | E26: Draft Released for Comment | F26: Full document | G26: No | H26: Pass 1 complete | J26: No
A27: 24 | B27: SWGDE Guidelines for Forensic Image Analysis (16-I-002-2.0) — Revision Summary v | C27: 2025 | D27: SWGDE Imaging | E27: Revision History (embedded) | F27: Revision history / change log section only (embedded in versioned PDF) | G27: No | H27: Pass 1 complete | J27: No
A28: 25 | B28: SWGDE Core Competencies for Mobile Device Forensics (12-F-003-2.0) — Five-Year R | C28: 2025 | D28: SWGDE Forensics | E28: Revision History (embedded) | F28: Revision history / change log section only (embedded in versioned PDF) | G28: Yes | H28: Pass 2 complete | I28: 10 | J28: Yes
A29: 26 | B29: SWGDE Guidelines for Forensic Image Analysis (16-I-002-2.0 Draft) — Draft for Pu | C29: 2024 | D29: SWGDE Imaging | E29: Draft Released for Comment | F29: Full document | G29: Yes | H29: Pass 1 complete | I29: 9 | J29: Yes
A30: 27 | B30: SWGDE Model Standard Operation Procedures (12-F-001-3.0) — Draft for Public Comm | C30: 2024 | D30: SWGDE Forensics | E30: Draft Released for Comment | F30: Full document | G30: No | H30: Pass 1 complete | J30: No
A31: 28 | B31: SWGDE Best Practices for Digital Forensic Video Analysis (18-V-001-1.1) — Archiv | C31: 2024 | D31: SWGDE Video | E31: Archived Version / Revision History | F31: Revision history / change log section only (embedded in versioned PDF) | G31: Yes | H31: Pass 2 complete | I31: 8 | J31: Yes
A32: 29 | B32: SWGDE Core Competencies for Digital Forensics (23-F-007-1.1) — Archived with Cha | C32: 2024 | D32: SWGDE Forensics | E32: Archived Version / Revision History | F32: Revision history / change log section only (embedded in versioned PDF) | G32: No | H32: Pass 1 complete | J32: No
A33: 30 | B33: SWGDE Core Competencies for Digital Forensics (12-F-006-2.0) — Published Final | C33: 2024 | D33: SWGDE Forensics | E33: Revision History (embedded) | F33: Revision history / change log section only (embedded in versioned PDF) | G33: No | H33: Pass 1 complete | J33: No
A34: 31 | B34: SWGDE Best Practices for Computer Forensic Acquisitions (17-F-002-2.0) — Revisio | C34: 2023 | D34: SWGDE Forensics | E34: Archived Version / Revision History | F34: Revision history / change log section only (embedded in versioned PDF) | G34: No | H34: Pass 1 complete | J34: No
A35: 32 | B35: SWGDE Technical Notes on FFmpeg for Forensic Audio Examination (23-A-001-1.0) | C35: 2023 | D35: SWGDE Audio | E35: Published Document (technical notes) | F35: Full document | G35: No | H35: Pass 1 complete | J35: No
A36: 33 | B36: SWGDE Test Method for Bluetooth Module Extraction (20-F-003-1.2) — Draft for Com | C36: 2023 | D36: SWGDE Forensics | E36: Draft Released for Comment | F36: Full document | G36: No | H36: Pass 1 complete | J36: No
A37: 34 | B37: SWGDE Training Guidelines for Video/Image Analysis and Photography (15-M-001-1.2 | C37: 2023 | D37: SWGDE Video | E37: Draft Released for Comment | F37: Full document | G37: Yes | H37: Pass 1 complete | I37: 6 | J37: Yes
A38: 35 | B38: SWGDE Best Practices for Video Authentication (23-V-001-1.2) — Revision History | C38: 2023 | D38: SWGDE Video | E38: Revision History (embedded) | F38: Revision history / change log section only (embedded in versioned PDF) | G38: No | H38: Pass 1 complete | J38: No
A39: 36 | B39: SWGDE Best Practices for On-Scene Identification, Seizure, and Preservation of I | C39: 2022 | D39: SWGDE Forensics | E39: Draft Released for Comment | F39: Full document | G39: Yes | H39: Pass 1 complete | I39: 4 | J39: Yes
A40: 37 | B40: SWGDE Introduction to Testimony in Digital and Multimedia Forensics (22-Q-001-1. | C40: 2022 | D40: SWGDE Quality | E40: Archived Version / Revision History | F40: Revision history / change log section only (embedded in versioned PDF) | G40: No | H40: Pass 1 complete | J40: No
A41: 40 | B41: SWGDE Establishing a Quality Management System (ISO-IEC 17025/17020 v2.0) — Comm | C41: 2021 | D41: SWGDE Quality | E41: Revision History (embedded) | F41: Revision history / change log section only (embedded in versioned PDF) | G41: No | H41: Pass 1 complete | J41: No
A42: 41 | B42: SWGDE Guidelines for Video Evidence Canvassing and Collection (v1.0) — Working G | C42: 2021 | D42: SWGDE Video | E42: Draft Released for Comment | F42: Full document | G42: No | H42: Pass 1 complete | J42: No
A43: 42 | B43: SWGDE Best Practices for Digital Evidence Acquisition from Cloud Service Provide | C43: 2020 | D43: SWGDE Forensics | E43: Draft Released for Comment | F43: Full document | G43: Yes | H43: Pass 1 complete | I43: 5 | J43: Yes
A44: 43 | B44: SWGDE Best Practices for Mobile Device Evidence Collection & Preservation (v1.2) | C44: 2020 | D44: SWGDE Forensics | E44: Archived Version / Revision History | F44: Revision history / change log section only (embedded in versioned PDF) | G44: No | H44: Pass 1 complete | J44: No
A45: 44 | B45: SWGDE Best Practice for Frame Timing Analysis of H.264 Video (v1.0) — Initial Pu | C45: 2020 | D45: SWGDE Video | E45: Draft Released for Comment | F45: Full document | G45: No | H45: Pass 1 complete | J45: No
A46: 45 | B46: SWGDE Practical Considerations for Submission and Presentation of Multimedia Evi | C46: 2020 | D46: SWGDE Quality | E46: Draft Released for Comment | F46: Full document | G46: Yes | H46: Pass 1 complete | J46: No
A47: C2 | B47: NIST OSAC FSSB Meeting Agendas — Public Sessions (2024, multiple quarters) | C47: 2024 | D47: NIST OSAC | E47: Meeting Agenda (Public) | F47: Full document | G47: No | H47: Not started | J47: No
A48: C3 | B48: NIST AI RMF Playbook — Stakeholder Workshop Summary Report | C48: 2023 | D48: NIST AI | E48: Working Group Notes / Workshop Summary | F48: Full document | G48: No | H48: Not started | J48: No
A49: C4 | B49: NIST IR 8596 iprd — Cyber AI Profile Public Comment Record and Comment Template | C49: 2025 | D49: NIST AI | E49: Public Comment Record / Comment Template | F49: Full document | G49: No | H49: Not started | J49: No
A50: C5 | B50: NIST OSAC Digital Evidence Subcommittee — R&D Needs Registry Entries | C50: 2020–2024 | D50: NIST OSAC | E50: Research Needs Report | F50: Full document | G50: No | H50: Not started | J50: No
A52: TOTALS | H52: =COUNTIF(H4:H51,"Pass 1 complete") -> 39 | I52: =SUM(I4:I51) -> 109 | J52: =COUNTIF(J4:J51,"Yes") -> 18

Sheet Memo Log
A1: Phase 2 Analytic Memo Log — Write after every 5 documents coded
A2: Memos document emerging patterns, code boundary decisions, unexpected findings, and tensions between codes. Required for reflexivity audit trail.
A3: Memo # | B3: Date | C3: After doc(s) # | D3: Emerging patterns / observations | E3: Code boundary decisions made | F3: Tensions / contradictions noted | G3: Action items (code changes, new EMER codes, etc.) | H3: Observations | I3: Document
A4: 1 | B4: 46122 | D4: Flag column R (memo note) for entry 7: Dominant pattern: ORG-01 as structural frame; TEC-01/TEC-06 recurring in validation sections; CRS-02 consistent throughout. 2.5-year history with zero prescriptive output. Compare against other SWGDE docs — is informational-only positioning a recurring organizational strategy? | E4: Flag column R (memo note) for entry 7: Dominant pattern: ORG-01 as structural frame; TEC-01/TEC-06 recurring in validation sections; CRS-02 consistent throughout. 2.5-year history with zero prescriptive output. Compare against other SWGDE docs — is informational-only positioning a recurring organizational strategy? | F4: Flag column R (memo note) for entry 7: Dominant pattern: ORG-01 as structural frame; TEC-01/TEC-06 recurring in validation sections; CRS-02 consistent throughout. 2.5-year history with zero prescriptive output. Compare against other SWGDE docs — is informational-only positioning a recurring organizational strategy? | G4: Flag column R (memo note) for entry 7: Dominant pattern: ORG-01 as structural frame; TEC-01/TEC-06 recurring in validation sections; CRS-02 consistent throughout. 2.5-year history with zero prescriptive output. Compare against other SWGDE docs — is informational-only positioning a recurring organizational strategy?
A5: 2 | B5: 46122 | C5: 38 | D5: Document #38 dominant pattern: ORG-06 (legal/admissibility concern) as primary structural mechanism — distinct from #39's ORG-01 framing. Both documents result in zero prescriptive confidence metrics but via different organizational logics. #38 knows measurement is needed ("standardized scale") but cannot specify it. Emerging cross-document pattern: SWGDE acknowledges AI output limitations consistently but organizational and legal constraints prevent measurement prescription. Compare with NIST documents for organizational barrier contrast. | E5: Document #38 dominant pattern: ORG-06 (legal/admissibility concern) as primary structural mechanism — distinct from #39's ORG-01 framing. Both documents result in zero prescriptive confidence metrics but via different organizational logics. #38 knows measurement is needed ("standardized scale") but cannot specify it. Emerging cross-document pattern: SWGDE acknowledges AI output limitations consistently but organizational and legal constraints prevent measurement prescription. Compare with NIST documents for organizational barrier contrast. | F5: Document #38 dominant pattern: ORG-06 (legal/admissibility concern) as primary structural mechanism — distinct from #39's ORG-01 framing. Both documents result in zero prescriptive confidence metrics but via different organizational logics. #38 knows measurement is needed ("standardized scale") but cannot specify it. Emerging cross-document pattern: SWGDE acknowledges AI output limitations consistently but organizational and legal constraints prevent measurement prescription. Compare with NIST documents for organizational barrier contrast. | G5: Document #38 dominant pattern: ORG-06 (legal/admissibility concern) as primary structural mechanism — distinct from #39's ORG-01 framing. Both documents result in zero prescriptive confidence metrics but via different organizational logics. #38 knows measurement is needed ("standardized scale") but cannot specify it. Emerging cross-document pattern: SWGDE acknowledges AI output limitations consistently but organizational and legal constraints prevent measurement prescription. Compare with NIST documents for organizational barrier contrast.
A6: 3 | B6: 46122 | D6: C1 dominant pattern: ORG-07 confirmed cross-quarter — AI is entirely absent from FSSB governance machinery across all four 2023 quarters at the task group, standards pipeline, and SAC action-item levels. December interpretation scales discussion (entry 18) is most significant finding — governance-level confidence measurement discussion explicitly scoped to exclude Digital/Multimedia SAC. Emerging cross-corpus pattern: OSAC institutional structure does not yet have a mechanism for AI governance in the digital forensics domain as of end of 2023. Compare with NIST AI RMF documents (#1, #3) for organizational contrast. | E6: C1 dominant pattern: ORG-07 confirmed cross-quarter — AI is entirely absent from FSSB governance machinery across all four 2023 quarters at the task group, standards pipeline, and SAC action-item levels. December interpretation scales discussion (entry 18) is most significant finding — governance-level confidence measurement discussion explicitly scoped to exclude Digital/Multimedia SAC. Emerging cross-corpus pattern: OSAC institutional structure does not yet have a mechanism for AI governance in the digital forensics domain as of end of 2023. Compare with NIST AI RMF documents (#1, #3) for organizational contrast. | F6: C1 dominant pattern: ORG-07 confirmed cross-quarter — AI is entirely absent from FSSB governance machinery across all four 2023 quarters at the task group, standards pipeline, and SAC action-item levels. December interpretation scales discussion (entry 18) is most significant finding — governance-level confidence measurement discussion explicitly scoped to exclude Digital/Multimedia SAC. Emerging cross-corpus pattern: OSAC institutional structure does not yet have a mechanism for AI governance in the digital forensics domain as of end of 2023. Compare with NIST AI RMF documents (#1, #3) for organizational contrast. | G6: C1 dominant pattern: ORG-07 confirmed cross-quarter — AI is entirely absent from FSSB governance machinery across all four 2023 quarters at the task group, standards pipeline, and SAC action-item levels. December interpretation scales discussion (entry 18) is most significant finding — governance-level confidence measurement discussion explicitly scoped to exclude Digital/Multimedia SAC. Emerging cross-corpus pattern: OSAC institutional structure does not yet have a mechanism for AI governance in the digital forensics domain as of end of 2023. Compare with NIST AI RMF documents (#1, #3) for organizational contrast.
A7: 4 | B7: 46122 | D7: Document #1 — access failure finding: EO 14110 rescission January 2025 rendered NIST AI RMF RFC public comment archive inaccessible. This is the only corpus document lost to governmental policy reversal rather than organizational scope decision or technical barrier. Coded PRO-02 + ORG-05 at document level. This finding has direct relevance to P2: even where AI governance standards development processes produced public records, those records are institutionally fragile and subject to political disruption. Cross-reference with CRS-04 (temporal marker — AI emergence period) — the 2020–2025 window is not just a period of AI standards development but also of AI governance instability at the federal level. Consider whether this warrants an emergent code: EMER-01 — Governmental policy reversal as process barrier (distinct from PRO-02 in that it is external and political rather than internal and procedural). | E7: Document #1 — access failure finding: EO 14110 rescission January 2025 rendered NIST AI RMF RFC public comment archive inaccessible. This is the only corpus document lost to governmental policy reversal rather than organizational scope decision or technical barrier. Coded PRO-02 + ORG-05 at document level. This finding has direct relevance to P2: even where AI governance standards development processes produced public records, those records are institutionally fragile and subject to political disruption. Cross-reference with CRS-04 (temporal marker — AI emergence period) — the 2020–2025 window is not just a period of AI standards development but also of AI governance instability at the federal level. Consider whether this warrants an emergent code: EMER-01 — Governmental policy reversal as process barrier (distinct from PRO-02 in that it is external and political rather than internal and procedural). | F7: Document #1 — access failure finding: EO 14110 rescission January 2025 rendered NIST AI RMF RFC public comment archive inaccessible. This is the only corpus document lost to governmental policy reversal rather than organizational scope decision or technical barrier. Coded PRO-02 + ORG-05 at document level. This finding has direct relevance to P2: even where AI governance standards development processes produced public records, those records are institutionally fragile and subject to political disruption. Cross-reference with CRS-04 (temporal marker — AI emergence period) — the 2020–2025 window is not just a period of AI standards development but also of AI governance instability at the federal level. Consider whether this warrants an emergent code: EMER-01 — Governmental policy reversal as process barrier (distinct from PRO-02 in that it is external and political rather than internal and procedural). | G7: Document #1 — access failure finding: EO 14110 rescission January 2025 rendered NIST AI RMF RFC public comment archive inaccessible. This is the only corpus document lost to governmental policy reversal rather than organizational scope decision or technical barrier. Coded PRO-02 + ORG-05 at document level. This finding has direct relevance to P2: even where AI governance standards development processes produced public records, those records are institutionally fragile and subject to political disruption. Cross-reference with CRS-04 (temporal marker — AI emergence period) — the 2020–2025 window is not just a period of AI standards development but also of AI governance instability at the federal level. Consider whether this warrants an emergent code: EMER-01 — Governmental policy reversal as process barrier (distinct from PRO-02 in that it is external and political rather than internal and procedural).
A8: 5 | B8: 46125 | C8: 16 | D8: Document #16 — most significant single-document finding in corpus: Digital Evidence Subcommittee has zero identified R&D needs (entry 22) — strongest ORG-07 finding to date. ANSI/ASTM E3016-18 confidence standard (directly addresses confidence in digital evidence forensic results) has been pending OSAC registry acceptance since 2018 — strongest PRO-02 in corpus and direct empirical support for P2. First SWGDE documents entered OSAC Registry only in FY23 after nine years — confirms ORG-05 institutional siloing between NIST and SWGDE is not just a documentation issue but a structural governance gap. Cross-corpus pattern now clearly established: organizational awareness gap (ORG-07) + process deadlock on the one existing confidence standard (PRO-02) + first-ever cross-organizational registry integration only in 2023 (ORG-05) = three convergent barriers that collectively explain why digital forensics AI confidence measurement has not advanced to prescriptive standards. This is your P2 confirmation pattern. | E8: Document #16 — most significant single-document finding in corpus: Digital Evidence Subcommittee has zero identified R&D needs (entry 22) — strongest ORG-07 finding to date. ANSI/ASTM E3016-18 confidence standard (directly addresses confidence in digital evidence forensic results) has been pending OSAC registry acceptance since 2018 — strongest PRO-02 in corpus and direct empirical support for P2. First SWGDE documents entered OSAC Registry only in FY23 after nine years — confirms ORG-05 institutional siloing between NIST and SWGDE is not just a documentation issue but a structural governance gap. Cross-corpus pattern now clearly established: organizational awareness gap (ORG-07) + process deadlock on the one existing confidence standard (PRO-02) + first-ever cross-organizational registry integration only in 2023 (ORG-05) = three convergent barriers that collectively explain why digital forensics AI confidence measurement has not advanced to prescriptive standards. This is your P2 confirmation pattern. | F8: Document #16 — most significant single-document finding in corpus: Digital Evidence Subcommittee has zero identified R&D needs (entry 22) — strongest ORG-07 finding to date. ANSI/ASTM E3016-18 confidence standard (directly addresses confidence in digital evidence forensic results) has been pending OSAC registry acceptance since 2018 — strongest PRO-02 in corpus and direct empirical support for P2. First SWGDE documents entered OSAC Registry only in FY23 after nine years — confirms ORG-05 institutional siloing between NIST and SWGDE is not just a documentation issue but a structural governance gap. Cross-corpus pattern now clearly established: organizational awareness gap (ORG-07) + process deadlock on the one existing confidence standard (PRO-02) + first-ever cross-organizational registry integration only in 2023 (ORG-05) = three convergent barriers that collectively explain why digital forensics AI confidence measurement has not advanced to prescriptive standards. This is your P2 confirmation pattern. | G8: Document #16 — most significant single-document finding in corpus: Digital Evidence Subcommittee has zero identified R&D needs (entry 22) — strongest ORG-07 finding to date. ANSI/ASTM E3016-18 confidence standard (directly addresses confidence in digital evidence forensic results) has been pending OSAC registry acceptance since 2018 — strongest PRO-02 in corpus and direct empirical support for P2. First SWGDE documents entered OSAC Registry only in FY23 after nine years — confirms ORG-05 institutional siloing between NIST and SWGDE is not just a documentation issue but a structural governance gap. Cross-corpus pattern now clearly established: organizational awareness gap (ORG-07) + process deadlock on the one existing confidence standard (PRO-02) + first-ever cross-organizational registry integration only in 2023 (ORG-05) = three convergent barriers that collectively explain why digital forensics AI confidence measurement has not advanced to prescriptive standards. This is your P2 confirmation pattern.
A9: 6 | B9: 46125 | D9: change Code 1 from PRO-02 to PRO-06. Write a one-line decision log entry explaining: "E3016-18 is an SDO-published standard that has not been accepted into the OSAC governance registry — this is a coordination failure between ASTM and OSAC, not an internal process stall. PRO-06 is more precise than PRO-02." | E9: change Code 1 from PRO-02 to PRO-06. Write a one-line decision log entry explaining: "E3016-18 is an SDO-published standard that has not been accepted into the OSAC governance registry — this is a coordination failure between ASTM and OSAC, not an internal process stall. PRO-06 is more precise than PRO-02." | F9: change Code 1 from PRO-02 to PRO-06. Write a one-line decision log entry explaining: "E3016-18 is an SDO-published standard that has not been accepted into the OSAC governance registry — this is a coordination failure between ASTM and OSAC, not an internal process stall. PRO-06 is more precise than PRO-02." | G9: change Code 1 from PRO-02 to PRO-06. Write a one-line decision log entry explaining: "E3016-18 is an SDO-published standard that has not been accepted into the OSAC governance registry — this is a coordination failure between ASTM and OSAC, not an internal process stall. PRO-06 is more precise than PRO-02."
A10: 7 | B10: 2026-04-13 | C10: 36 | D10: Doc 36 dominant pattern: ORG-01 (scope exclusion) as primary frame — AI/confidence measurement excluded by design, not omission. TEC-01/TEC-02 present in preservation/collection sections without resolution. ORG-02 + PRO-02 co-occur in §9 confirming resource-process barrier dyad. Zero prescriptive confidence output. | E10: ORG-01 vs ORG-07: Doc 36 excludes AI by scope design (ORG-01), not because the organization lacks awareness (ORG-07) — scope exclusion is the more precise code here. | F10: Three SWGDE exclusion logics now confirmed: Doc 39 = informational positioning (ORG-01); Doc 38 = legal constraint (ORG-06); Doc 36 = operational scope (ORG-01). All produce zero prescriptive confidence output but via distinct institutional mechanisms. | G10: No new EMER codes required. ORG-02 + PRO-02 dyad in §9 is consistent with existing codebook. Flag for cross-document pattern analysis in final memo.
A11: 8 | B11: 2026-04-13 | C11: 42 | D11: Doc 42 dominant pattern: ORG-01 + ORG-06 dual exclusion in §3 now confirmed third consecutive SWGDE document (Docs #36, #38, #42). Hash verification (TEC-03/CRS-02) only integrity mechanism — contingent on provider cooperation. PRO-01: zero edits after public comment across 14-month cycle. Leanest codeable document in corpus. | E11: TEC-03 vs TEC-01: hash verification is an integrity check (TEC-03), not a confidence measurement gap (TEC-01) — no AI output being assessed here; distinction holds. | F11: ORG-01 + ORG-06 co-occurrence in §3 is now a confirmed SWGDE structural pattern across at least three documents. Cross-corpus pattern: SWGDE best practices documents open with dual scope/legal exclusion and produce zero prescriptive confidence output regardless of domain (IoT, cloud, facial recognition). | G11: No new EMER codes. Flag ORG-01+ORG-06 dyad as candidate theme node for P2 findings synthesis.
A12: 9 | B12: 46127 | C12: 34 | D12: Document-level pattern: ORG-01 (scope exclusion) + TEC-01 (measurement complexity) are co-dominant. TEC-02 present at §5. PRO-01 confirmed via revision history. No AI-specific content (publication date 2016). CRS-02 flags cluster around §3, §9, and §10.5/10.7 — competency/proficiency definitions acknowledge measurement without operationalizing it. | E12: Document-level pattern: ORG-01 (scope exclusion) + TEC-01 (measurement complexity) are co-dominant. TEC-02 present at §5. PRO-01 confirmed via revision history. No AI-specific content (publication date 2016). CRS-02 flags cluster around §3, §9, and §10.5/10.7 — competency/proficiency definitions acknowledge measurement without operationalizing it. | F12: Document-level pattern: ORG-01 (scope exclusion) + TEC-01 (measurement complexity) are co-dominant. TEC-02 present at §5. PRO-01 confirmed via revision history. No AI-specific content (publication date 2016). CRS-02 flags cluster around §3, §9, and §10.5/10.7 — competency/proficiency definitions acknowledge measurement without operationalizing it. | G12: Document-level pattern: ORG-01 (scope exclusion) + TEC-01 (measurement complexity) are co-dominant. TEC-02 present at §5. PRO-01 confirmed via revision history. No AI-specific content (publication date 2016). CRS-02 flags cluster around §3, §9, and §10.5/10.7 — competency/proficiency definitions acknowledge measurement without operationalizing it.
A13: 10 | B13: 46127 | C13: 6 | D13: Doc #6 is analytically the most important NIST document coded so far for your P1/P2 cross-phase integration. Three findings dominate. First, the technology-neutral design principle (Entry 67) is the most explicit institutional statement in the corpus of a design choice that produces the AIDFIR gap. It is not an oversight — it is an architectural decision. Second, RA-3(4) Predictive Cyber Analytics (Entry 68) is the sole AI-specific control enhancement in a 492-page document, and it prescribes human oversight as the AI reliability response rather than a validation protocol. Third, the assurance definition in §2.5 (Entry 65) establishes that confidence measurement is conceptually present in NIST's framework but deferred to SP 800-53A — a cross-document dependency that is itself a PRO-01 pattern. | E13: Entry 67 receives both ORG-01 and TEC-02 — these are not redundant. ORG-01 captures the institutional scope decision; TEC-02 captures the methodological consequence for AI validation. The CRS-01 flag at Entry 67 is warranted because the technology-neutral principle is the most direct statement of why AI-specific confidence guidance is absent. Entry 68 receives TEC-06 (first activation in a NIST document) alongside TEC-01 — the adversarial model retraining risk is an opacity/explainability problem before it is a measurement complexity problem. | F13: The validated-without-definition pattern at Entry 70 (SI-19(7)) is the federal-level analog of Doc #34's "validated technologies" requirement (SWGDE Entry 43). Both mandate validation as a principle; neither specifies a methodology. This cross-corpus parallel directly supports your TEC-02 finding. The PRO-01 errata pattern (Entry 71) continues the multi-document pattern: one revision cycle, editorial only, zero AI-specific content additions — now confirmed across NIST (Doc #6) and SWGDE (Docs #34, #42, #45) revision records. | G13: Doc #6 has higher D1 and D3 scores than most SWGDE documents (both score 2) because NIST conceptually addresses assurance and validation evidence. But D4 collapses both to 1 via the min-score rule. This is analytically important: NIST's greater conceptual sophistication on confidence and reproducibility makes the AI-specific gap more visible, not less. A document that knows what assurance means and still cannot provide AI-specific assurance guidance is a stronger demonstration of the gap than a document that never addresses the concept.
A14: 11 | B14: 46127 | C14: 10 | D14: Doc #10 is the most technically rich document in the corpus and produces the corpus's strongest TEC-01, TEC-04, and TEC-06 evidence. Three findings dominate. First, the mathematical impossibility argument (Entry 74): ML systems have no information-theoretic security proofs, which means AI confidence claims are structurally different from — and weaker than — the validated tool claims forensic examiners currently use. This is not a process gap but a theoretical one. Second, the risk tolerance non-recommendation (Entry 73): NIST explicitly names the concept forensic practitioners most need (when is AI risk acceptable?) and declines to answer it by design. Third, the benchmark incomparability finding (Entry 77): AI validation evidence is not merely sparse but structurally incomparable — results from different research groups cannot be aggregated because there are no standardized benchmarks. | E14: Entry 73 receives both ORG-01 and TEC-01. ORG-01 captures the institutional decision not to address risk tolerance; TEC-01 captures the technical rationale given (context-dependency). These are not redundant — the institutional decision could in principle be reversed even if the technical argument is valid. Entry 76 receives TEC-02 and TEC-06. The "ad hoc and fallible" characterization of mitigation design is TEC-02 (validation methodology gap); the inability to detect model compromise is TEC-06 (opacity barrier). Entry 78 receives TEC-01 and TEC-02 — the theoretical limits on testing are a measurement problem (TEC-01); the absence of specified measures beyond adversarial testing is a validation methodology gap (TEC-02). | F14: Doc #10 Entry 74 (no information-theoretic proofs for ML) provides the theoretical explanation for Doc #3 Entry 47 (measurement science "generally immature") and Doc #6 Entry 65 (assurance definition without operationalization). These three entries together form your complete theoretical-to-definitional-to-operational account of the D1 gap: immature measurement science (Doc #3) → formal proof impossibility (Doc #10) → assurance concept without method (Doc #6). The PRO-04 pattern at Entries 77 and 79 is the fourth document to close with deferral language — joining Doc #3 (Entry 55), Doc #13 (Entry 62), and Doc #6 (Entry 71). PRO-04 is now confirmed as a multi-document cross-organizational pattern, not a single-document artifact. | G14: Pareto constraint on confidence standards (Entry 75): The Pareto trade-off between accuracy, robustness, and fairness has not been explicitly theorized in prior corpus documents. This is the most technically sophisticated statement in the corpus of why a single-dimensional confidence metric cannot adequately validate a forensic AI tool. Consider whether this warrants a CRS sub-code or a memo-level observation that feeds into your cross-phase synthesis. | H14: Doc #10 scores 2 on all four dimensions — the first corpus document at that profile. This is analytically important: NIST AI 100-2 is the most AI-specific, most technically engaged document in the corpus, and it still cannot break above D4 = 2. The score of 2 reflects substantial conceptual engagement without prescriptive resolution. Your min-score rule appropriately captures this — 2 across all dimensions is a better outcome than 1 with a D4 ceiling, but it confirms that even the most sophisticated AI security documentation falls well short of the operational confidence measurement guidance your AIDFIR framework identifies as needed.
A15: 12 | B15: 46127 | C15: 4
A16: 13 | B16: 46127 | C16: 1 | D16: EMER-01 status: memo correctly says hold, do not activate. That decision stands. No action needed, but confirm you have a decision log entry written for this.
A17: 14 | B17: 46127 | C17: C1 | D17: Entry 16 (Doc C1) — ORG-03 provisional "?": Your memo notes this cannot be resolved without Doc C5 context. That is correctly flagged. No action now — but add a cross-reference note in your memo column pointing to "resolve pending C5 coding."
A18: 15 | B18: 46128 | C18: 7 | D18: Document-Level Pattern Note (Doc #7) Doc #7 presents a distinctive and analytically significant pattern not previously seen in the corpus: it is the only document where the revision history documents a deliberate retreat from prescriptive operational content. The ORG-01 + PRO-03 co-occurrence at entries 92 and 97 is reinforced by the explicit Change Log, which constitutes institutional documentary evidence — not inference — that the AIDFIR-relevant content space was actively narrowed. The CRS-01 flag at entry 95 (sole AI reference, parenthetical) confirms that by 2025, a major NIST incident response publication still had not integrated AI-specific guidance despite clear operational relevance. Together these entries contribute a third barrier logic to the NIST SP 800 sub-corpus alongside the voluntary-framing ORG-01 (Docs #3, #6, #10) and hub-and-spoke PRO-06 (Docs #4, #5): active prescriptive retraction. New codes generated: 0. All codes used (ORG-01, ORG-07, TEC-01, TEC-02, PRO-03, PRO-06, CRS-01, CRS-02, ORG-06) are existing codebook entries. Update saturation tracker accordingly.
A19: 16 | B19: 46128 | C19: 20 | D19: Document-Level Pattern Note (Doc #20) Doc #20 produces 0 new codes — all six codes applied (ORG-01, TEC-01, TEC-02, TEC-06, PRO-06, CRS-02) are established codebook entries. This is the second consecutive no-new-code document (after Doc #7). Analytically, however, the document is not merely confirmatory — it adds a new logical layer to existing patterns. The scope exclusion of deployment/operation (entry 98) is the most precisely AIDFIR-targeted ORG-01 in the corpus. The "art not science" framing (entry 100) is the strongest TEC-01 expression. The evidence/artifact passage (entry 103) is the clearest single-passage crystallization of the AIDFIR gap in NIST language. Saturation tracker update: 2 consecutive documents with no new codes (Docs #7 and #20). One more no-new-code document confirms saturation under your three-consecutive stopping rule.
A20: 17 | B20: 46128 | C20: 13 | D20: Document-Level Pattern Note (Doc #13) Doc #13 produces 0 new codes. All codes applied (ORG-01, TEC-01, TEC-02, TEC-06, PRO-03, PRO-04, CRS-01, CRS-02) are established codebook entries. This is the third consecutive no-new-code document (Docs #7, #20, #13). Saturation is confirmed. Under your three-consecutive stopping rule, you may now formally declare theoretical saturation and cease coding new Tier 2 documents. Document this in your Emerging Patterns sheet. The saturation declaration does not diminish Doc #13's analytical value — it is the richest single document for dissertation quotation in the corpus. Entry 108 (confidence thresholds named without specification) and entry 110 (AI forensics named without elaboration) are the two passages that most directly name the AIDFIR gap in NIST's own language as of 2025. These should anchor your Phase 2 findings section. Remaining work: Tier 1 κ documents #21, #25, #26, #28 only. Saturation sampling is complete.
A21: 18 | B21: 46129 | C21: 15 | D21: Document TEC-04 as a late-emerging, empirically-gated code and proceed. Add a methodological note to the analysis chapter explaining why TEC-04 activated late (empirical documents are rare in the sub-corpus) and what that structure tells us (the AIDFIR gap includes a performance-reporting gap at the institutional level). | H21: Saturation check Codes used in Doc #15: ORG-02, ORG-07, TEC-01, TEC-04, TEC-05, TEC-06, TEC-02, PRO-04, CRS-02 New codes activated: 1 — TEC-04 (Insufficient empirical base).
A22: 19 | B22: 46129 | C22: 25 | G22: Reclassification note Doc #25 in the original corpus registry was specified as "SWGDE Core Competencies for Mobile Device Forensics (12-F-003-2.0) — Five-Year Review Notes." SWGDE did not publish a separate five-year review artifact for this document; the publicly available revision-trail artifact is the §7 History Table embedded within the final v2.0 standard. Per purposive saturation sampling design and κ subsample reliability requirements, Doc #25 is coded using this embedded History Table as the proxy artifact, supplemented by targeted content sampling where the competencies enumeration itself provides evidence bearing on Phase 2 codes.
A23: 20 | B23: 46129 | C23: 28 | D23: The triad establishes a controlled institutional experiment in the dissertation's evidentiary base: the 2024–2025 revision window had declared scope coverage of AI-natural sections (Doc #21 entry 134), had demonstrated capacity to add examination types (Doc #28 entry 142 vs. Doc #68 entry 113), and chose to add Photogrammetric Analysis and Content Analysis while not adding any AI/ML examination category. This is not a null finding by absence — it is a positive finding of selective non-adoption: the revision institutionally could have added AI content, documented that it would consider adding examination content, added two non-AI examination categories, and did not add AI. For the dissertation: this is the strongest structured evidentiary chain in the corpus for the argument that the AIDFIR gap in SWGDE operational standards is an active outcome of revision-cycle choices rather than a passive lag.
A24: 21 | B24: 46129 | C24: 26 | G24: κ considerations. Doc #26 is in the κ subsample. Pass 1 codes logged above. Pass 2 would test whether Entry 111 (TEC-06 + ORG-05 co-occurrence on the deepfake passage) and Entry 115 (TEC-01 + PRO-06 + CRS-02 on the dropped graded scale) are coded consistently on re-review — these are the two most judgment-heavy decisions in the document. (Note: per your April 2026 protocol amendment, Pass 2 κ has been withdrawn in favor of the Lincoln & Guba dependability audit trail. The reliability record for this document is the documented coding rationale above.)
A25: 22 | B25: 46129 | D25: Emerging Pattern/Saturation Recorded. See Emerging Pattern Tab for additional naturative
A26: 23 | B26: 46130 | C26: 4 | H26: Registry anomaly memo note (methodological): Registry row 4 records the title "NIST CSF 2.0 — Public Comment Analysis Report" and artifact type "Public Comment Record," but the registry URL points to the February 26, 2024 NIST CSF 2.0 release press release. Web search conducted 4/18/2026 did not surface any discrete standalone "NIST CSF 2.0 Public Comment Analysis Report" document; NIST's CSF 2.0 disposition model posted comments to the CSF 2.0 website and reflected feedback in redrafts rather than publishing a consolidated response-to-comments artifact. Per Path A selected by coder, the artifact identified by the registry URL was coded as Doc #4, and the registry title/artifact-type fields should be corrected to reflect the press-release artifact in a future registry maintenance pass. No Decision Log amendment is required because the κ sample and the artifact actually coded are unchanged; this is a metadata-field correction. The anomaly itself is dependability audit trail evidence — transparent documentation of a registry-integrity issue caught at coding time. | I26: Part 3 — Document-Level Memos (Longitudinal Analysis) Saturation status for this document. Codes activated: ORG-01, ORG-02, ORG-05, PRO-01, PRO-02, PRO-03, PRO-04, TEC-01, TEC-02, CRS-02. All previously active. Zero new codes. Zero codebook refinements. Consistent with post-saturation κ-subsample expectations per Decision Log Amendment #2. Longitudinal-pair methodology note (audit trail): Doc #28 (SWGDE 18-V-001-1.1, 3/22/2024) and Doc #21 (SWGDE 18-V-001-2.0, 12/10/2025) are the same document at two different revision states, 21 months apart. The longitudinal pair was identified at coding time for Doc #28 (4/18/2026) based on shared SWGDE identifier, title, and Doc #21's revision-history table. Coding approach per Path A (selected by coder on 4/18/2026): Part 1 rubric scored standalone per Phase 1 methodology; Part 2 entries focused on revision-delta passages and v1.1-unique content; Part 3 memos framed as longitudinal analysis. This approach preserves audit-trail integrity (documents are independently scored for Phase 1 QUAN data) while avoiding redundant Part 2 entries on near-identical passages. Near-identical passages in both versions were not re-coded in Doc #28 (they were coded in Doc #21 entries #126–#136); this design choice is documented here as dependability audit trail evidence. No Decision Log amendment is required because the κ sample and coding methodology are unchanged; this is a within-κ analytical approach adapted to the longitudinal pair. Primary longitudinal findings: The AIDFIR gap was structurally preserved through a substantive revision window. The 21-month window between Doc #28 (3/22/2024) and Doc #21 (12/10/2025) brackets exactly the period in which generative-AI threat awareness became mainstream in forensic-science standards discourse (OSAC's 9/16/2024 request for evaluation of this document; NIST AI 600-1 release 7/26/2024; the U.S. Department of Justice's late-2024 and 2025 deepfake-related guidance). SWGDE had the organizational opportunity, external triggering event (OSAC), and revision-scope latitude (expanded taxonomy, added procedural subsections, uplifted prescriptive documentation language) to incorporate AI-validation content. It did not. The gap is preserved through the revision, not merely across the revision cadence. The v2.0 revision demonstrably expanded scope — but in non-AI directions. Concrete v2.0 additions identified across Entries 148–153 include: added Photogrammetric Analysis and Content Analysis examination categories; new legal-authority verification step at §4.1; new §4.3.3.1 Transcoding subsection with Lossless/Lossy granularity; new "shall document discrepancies" prescriptive language at §4.3.3; expanded clarification-technique enumeration (deinterlacing, deblocking, spatial-frequency filtering); new §4.3.5 Further Analysis subsection; expanded reference network from 12 to 15 documents. Each addition represents a point where SWGDE had editorial attention focused on a specific scope area and chose to extend that area without incorporating AI-related content. This is selective non-incorporation, not passive non-update. Competency framework null-delta is the strongest single piece of P1 evidence in the corpus. Entry 154 documents that the analyst-competency enumeration was not substantively revised between v1.1 and v2.0. Competency requirements govern who can perform forensic video analysis, what knowledge they must demonstrate, and what their training must cover. SWGDE had 21 months and an OSAC-driven substantive revision to update competency requirements to reflect AI-related threats and AI-assisted tooling. The framework was unchanged. This is null-delta evidence with direct operational consequence: analysts trained to SWGDE 18-V-001 v2.0 (Dec 2025) are subject to the same AI-naive competency bar as analysts trained to v1.1 (Mar 2024). D-dimension score stability across revision. Phase 1 QUAN scores for the longitudinal pair: D1 unchanged (1→1), D2 marginally uplifted (1→2) via added discrepancy-documentation language, D3 unchanged (3→3 — ceiling was already reached in v1.1), D4 unchanged (1→1). Document score unchanged (1→1). The revision produced measurable rubric change only on D2, and that change was a side-effect of procedural-language tightening, not intentional error-rate quantification uplift. The overall P1-relevant finding: even substantive SWGDE revisions do not move the D4 needle. This is directly supportive of P1's update-frequency mechanism proposition and sharpens it — the mechanism is not just about raw cadence, it's about revision-scope not including AI even when revision occurs. Corpus implication: κ-subsample now has two instances of the same document family. The dependability audit trail now documents (a) within-document coder stability across v1.1 and v2.0 (entries on near-identical passages match between Doc #28 and Doc #21 — e.g., §4.4.1 Opinions language, §7.4 Documentation language, §5.1 Storage Media), and (b) coder's ability to distinguish substantive vs. non-substantive revision changes. Both are useful dependability evidence under Lincoln & Guba (1985). Cross-references for dissertation write-up: The longitudinal pair (Doc #28 ↔ Doc #21) should be presented in Chapter 5 as the centerpiece empirical illustration of the "structurally preserved gap through substantive revision" finding. This is the cleanest within-document evidence for P1 in the corpus. Competency null-delta (Entry 154) → pair with Doc #25 §5.2 foundational-skills enumeration (Entry 141). Three-document cross-reference: SWGDE's competency-framework architecture (Doc #25 mobile + Doc #28/#21 video) does not contain AI content as of mid-2025, and did not acquire it through the revisions available in the window. Revision-scope-expansion-without-AI pattern (Memo #2) → Chapter 5 subsection on "scope uplift without AI inclusion" as a structural D4-gap preservation mechanism. Distinct from but complementary to the "stay current" mechanism (Doc #25 Memo #1) and the delegation-network depth mechanism (Doc #21 Memo #4). D-dimension stability (Memo #4) → Phase 1 results robustness check. The longitudinal pair provides within-document QUAN evidence that SWGDE rubric scores are stable across revisions — strengthening the cross-sectional Phase 1 findings.
A27: 24 | B27: 46130 | C27: 21
A28: 25 | B28: 46130 | C28: 28
A29: 26 | B29: 46130 | C29: 6 | D29: Emerging Patterns sheet: "Doc #6 (NIST SP 800-53 Rev. 5) was coded 4/15/2026, prior to saturation declaration (4/17/2026), and contributed to codebook development including the first TEC-06 activation via control RA-3(4). Doc #6 is documented as a codebook-constitutive document, not a post-saturation dependability-audit document. The κ subsample floor specified in Decision Log Amendment #2 is met by Docs #10, #26, #4, #21, #25, and #28, all coded post-saturation under a frozen codebook."
B30: 46130 | C30: 6 | D30: Memo #14 — Doc #6 Methodological Position (Codebook-Constitutive Documentation) Date: 2026-04-18 Purpose: Document the methodological position of Doc #6 within the Phase 2 QUAL coding protocol and κ-subsample architecture. Context. Doc #6 (NIST SP 800-53 Rev. 5) was coded on 2026-04-15 as part of the initial Phase 2 inductive coding work, producing nine entries (#63–#71). Review of the coding session indicates Doc #6 contributed substantively to codebook development, including the first TEC-06 activation in the corpus via control RA-3(4) (Entry #68) and the most explicit corpus-level statement of technology-neutral design as an AIDFIR-gap source (Entry #67). Doc #6 was coded prior to the saturation declaration (2026-04-17) documented under Decision Log Amendment #2 (2026-04-14). Methodological position. Doc #6 is documented as a codebook-constitutive document rather than a post-saturation dependability-audit document. Entries #63–#71 contributed to the operational definition and instantiation of codes active in the frozen codebook, and therefore cannot serve as independent dependability evidence for those same codes under Lincoln & Guba (1985). The codebook-constitutive role is analytically legitimate and the entries remain in the Coding Log in full. κ-subsample status. The six-document κ-subsample floor specified in Decision Log Amendment #2 is met by post-saturation coded documents only: Doc #10 — NIST AI 100-2e2025 (coded 2026-04-15, recognized as within-saturation coding alongside codebook-development work) Doc #26 — SWGDE 16-I-002-2.0 Forensic Image Analysis Draft (coded 2026-04-17, post-saturation) Doc #4 — NIST CSF 2.0 Release Announcement (coded 2026-04-18, post-saturation) Doc #21 — SWGDE 18-V-001-2.0 Digital Forensic Video Analysis (coded 2026-04-18, post-saturation) Doc #25 — SWGDE 12-F-003-2.0 Core Competencies for Mobile Device Forensics (coded 2026-04-18, post-saturation) Doc #28 — SWGDE 18-V-001-1.1 Digital Forensic Video Analysis (coded 2026-04-18, post-saturation, longitudinal pair with Doc #21) All six floor documents were coded under a frozen codebook with zero new codes introduced, consistent with Lincoln & Guba (1985) dependability audit trail conditions. Note on Doc #10. Doc #10 was coded on 4/15/2026 in the same session as Doc #6 but produced no new codes beyond those already active in the codebook at that time; it is positioned as a within-saturation κ-subsample document rather than a codebook-constitutive document. This distinction is preserved in the audit trail. Rationale for Path C selection. Re-coding Doc #6 as an intra-rater stability check (the Lincoln & Guba-aligned alternative) was considered and declined because (a) the three-day interval between original coding (4/15) and potential re-coding (4/18) is shorter than the stability-check blindness window typically recommended, (b) the codebook-constitutive status of Entry #68 (first TEC-06 activation) cannot be methodologically undone by re-coding, and (c) the κ-subsample floor is satisfied without Doc #6 inclusion in the post-saturation set. Transparent documentation of the codebook-constitutive vs. dependability-audit distinction constitutes stronger methodological reflexivity than forced re-coding. Methodological citation. Lincoln, Y. S., & Guba, E. G. (1985). Naturalistic inquiry. Sage. Cross-references. Decision Log Amendment #2 (2026-04-14); Emerging Patterns sheet saturation-declaration entry (2026-04-17); Coding Log entries #63–#71 (Doc #6, 2026-04-15).

Sheet κ Subsample Tracker
A1: Phase 2 Intra-rater κ Subsample Tracker | Seed = 808 | n = 16 | κ ≥ 0.70 target | ≥ 14-day gap between Pass 1 and Pass 2
A2: Per Morse (2016): κ ≥ 0.70 = acceptable; κ ≥ 0.80 = strong. If κ < 0.70 on any domain: revise code definitions → recode subsample → recalculate before full corpus coding.
A3: κ subsample docs (selected seed=808): #36, #42, #34, #45, #26, #14, #4, #3, #25, #28, #21, #6, #10, #16, #13, #39 | Pass 1 target date: ______ | Pass 2 target date (Pass 1 + 14d minimum): ______
A4: Doc # | B4: Title (short) | C4: Source | D4: Stratum | E4: Coding unit | F4: Pass 1 — Code 1 | G4: Pass 1 — Code 2 | H4: Pass 1 — Code 3 | I4: Pass 1 — CRS | J4: Pass 2 — Code 1 | K4: Pass 2 — Code 2 | L4: Pass 2 — Code 3 | M4: Pass 2 — CRS | N4: Match? (auto)
A5: 36 | B5: SWGDE Best Practices for On-Scene Identification, Seizure, and Preservation of I | C5: SWGDE Forensics | D5: SWGDE drafts for comment | E5: Full document | N5: =IF(AND(F5=J5,G5=K5,H5=L5,I5=M5),"✓ Match","✗ Diff") -> ✓ Match
A6: 42 | B6: SWGDE Best Practices for Digital Evidence Acquisition from Cloud Service Provide | C6: SWGDE Forensics | D6: SWGDE drafts for comment | E6: Full document | N6: =IF(AND(F6=J6,G6=K6,H6=L6,I6=M6),"✓ Match","✗ Diff") -> ✓ Match
A7: 34 | B7: SWGDE Training Guidelines for Video/Image Analysis and Photography (15-M-001-1.2 | C7: SWGDE Video | D7: SWGDE drafts for comment | E7: Full document | N7: =IF(AND(F7=J7,G7=K7,H7=L7,I7=M7),"✓ Match","✗ Diff") -> ✓ Match
A8: 45 | B8: SWGDE Practical Considerations for Submission and Presentation of Multimedia Evi | C8: SWGDE Quality | D8: SWGDE drafts for comment | E8: Full document | N8: =IF(AND(F8=J8,G8=K8,H8=L8,I8=M8),"✓ Match","✗ Diff") -> ✓ Match
A9: 26 | B9: SWGDE Guidelines for Forensic Image Analysis (16-I-002-2.0 Draft) — Draft for Pu | C9: SWGDE Imaging | D9: SWGDE drafts for comment | E9: Full document | N9: =IF(AND(F9=J9,G9=K9,H9=L9,I9=M9),"✓ Match","✗ Diff") -> ✓ Match
A10: 14 | B10: NIST AI 100-4 (Synthetic Content) — Public Workshop and Stakeholder Feedback | C10: NIST AI | D10: NIST public comment records | E10: Full document | N10: =IF(AND(F10=J10,G10=K10,H10=L10,I10=M10),"✓ Match","✗ Diff") -> ✓ Match
A11: 4 | B11: NIST CSF 2.0 — Public Comment Analysis Report | C11: NIST CSF | D11: NIST public comment records | E11: Full document | N11: =IF(AND(F11=J11,G11=K11,H11=L11,I11=M11),"✓ Match","✗ Diff") -> ✓ Match
A12: 3 | B12: NIST AI 600-1 (Generative AI) — Public Comment Summary | C12: NIST AI | D12: NIST public comment records | E12: Full document | N12: =IF(AND(F12=J12,G12=K12,H12=L12,I12=M12),"✓ Match","✗ Diff") -> ✓ Match
A13: 25 | B13: SWGDE Core Competencies for Mobile Device Forensics (12-F-003-2.0) — Five-Year R | C13: SWGDE Forensics | D13: Revision histories both sources | E13: Revision history / change log section only (embedded in versioned PDF) | N13: =IF(AND(F13=J13,G13=K13,H13=L13,I13=M13),"✓ Match","✗ Diff") -> ✓ Match
A14: 28 | B14: SWGDE Best Practices for Digital Forensic Video Analysis (18-V-001-1.1) — Archiv | C14: SWGDE Video | D14: Revision histories both sources | E14: Revision history / change log section only (embedded in versioned PDF) | N14: =IF(AND(F14=J14,G14=K14,H14=L14,I14=M14),"✓ Match","✗ Diff") -> ✓ Match
A15: 21 | B15: SWGDE Best Practices for Digital Forensic Video Analysis (18-V-001-2.0) — Revisi | C15: SWGDE Video | D15: Revision histories both sources | E15: Revision history / change log section only (embedded in versioned PDF) | N15: =IF(AND(F15=J15,G15=K15,H15=L15,I15=M15),"✓ Match","✗ Diff") -> ✓ Match
A16: 6 | B16: NIST SP 800-53 Rev 5 — Comment Disposition Report | C16: NIST SP 800 | D16: NIST comment disposition reports | E16: AI- and confidence-relevant comment threads only (large-volume CDR — apply within-document sampling) | N16: =IF(AND(F16=J16,G16=K16,H16=L16,I16=M16),"✓ Match","✗ Diff") -> ✓ Match
... A20: 39 | B20: SWGDE Overview: Artificial Intelligence Trends in Video Analysis (v1.0) | C20: SWGDE Video | D20: Published AI-specific | E20: Full document | N20: =IF(AND(F20=J20,G20=K20,H20=L20,I20=M20),"✓ Match","✗ Diff") -> ✓ Match
A22: κ SUMMARY — Complete after Pass 2
A23: Total passages in subsample | F23: =COUNTA(F5:F21) -> 0
A24: Agreed passages (Pass 1 = Pass 2, Code 1) | F24: =COUNTIF(N5:N21,"✓ Match") -> 16
A25: Percent agreement | F25: =IFERROR(IF(F23>0,F24/F23,""),"") | K25: Target ≥ 70%
A26: Cohen's κ (calculate manually — see formula) | F26: Enter calculated κ → | K26: κ = (Po − Pe) / (1 − Pe)
A27: Overall result | K27: PASS (κ ≥ 0.70) or FAIL — enter manually
A28: ORG domain κ | K28: Enter after domain-level calculation
A29: TEC domain κ | K29: Enter after domain-level calculation
A30: PRO domain κ | K30: Enter after domain-level calculation
A31: Decision | K31: If PASS: proceed to full corpus. If FAIL: revise definitions → recode → recalculate.
A33: 46130 | B33: κ-subsample floor met With Doc #28 complete, the six-document κ-subsample floor specified in Decision Log Amendment #2 (2026-04-14) has been met: Doc #10 (NIST AI 100-2e2025) — coded 4/15/2026 Doc #26 (SWGDE 16-I-002-2.0) — coded 4/17/2026 Doc #4 (NIST CSF 2.0 Release Announcement) — coded 4/18/2026 Doc #21 (SWGDE 18-V-001-2.0) — coded 4/18/2026 Doc #25 (SWGDE 12-F-003-2.0) — coded 4/18/2026 Doc #28 (SWGDE 18-V-001-1.1) — coded 4/18/2026

Sheet Code Frequency
A1: Code Frequency Summary — Update after full corpus coding complete
A2: Count passages per code from Coding Log. COUNTIF formulas reference the Coding Log sheet — recalculate after each coding session.
A3: Domain | B3: Code | C3: Label | D3: Count (Code 1 col) | E3: Count (Code 2 col) | F3: Total
A4: Domain ORG
A5: ORG | B5: ORG-01 | C5: Scope exclusion | D5: =COUNTIF('Coding Log'!J:J,"ORG-01") -> 26 | E5: =COUNTIF('Coding Log'!K:K,"ORG-01") -> 3 | F5: =D5+E5 -> 29
A6: ORG | B6: ORG-02 | C6: Resource constraint | D6: =COUNTIF('Coding Log'!J:J,"ORG-02") -> 5 | E6: =COUNTIF('Coding Log'!K:K,"ORG-02") -> 1 | F6: =D6+E6 -> 6
A7: ORG | B7: ORG-03 | C7: Competing priorities | D7: =COUNTIF('Coding Log'!J:J,"ORG-03") -> 2 | E7: =COUNTIF('Coding Log'!K:K,"ORG-03") -> 0 | F7: =D7+E7 -> 2
A8: ORG | B8: ORG-04 | C8: Stakeholder consensus failure | D8: =COUNTIF('Coding Log'!J:J,"ORG-04") -> 0 | E8: =COUNTIF('Coding Log'!K:K,"ORG-04") -> 1 | F8: =D8+E8 -> 1
A9: ORG | B9: ORG-05 | C9: Institutional siloing | D9: =COUNTIF('Coding Log'!J:J,"ORG-05") -> 8 | E9: =COUNTIF('Coding Log'!K:K,"ORG-05") -> 6 | F9: =D9+E9 -> 14
A10: ORG | B10: ORG-06 | C10: Legal / admissibility concern | D10: =COUNTIF('Coding Log'!J:J,"ORG-06") -> 3 | E10: =COUNTIF('Coding Log'!K:K,"ORG-06") -> 1 | F10: =D10+E10 -> 4
A11: ORG | B11: ORG-07 | C11: AI awareness gap | D11: =COUNTIF('Coding Log'!J:J,"ORG-07") -> 12 | E11: =COUNTIF('Coding Log'!K:K,"ORG-07") -> 5 | F11: =D11+E11 -> 17
A12: Domain TEC
A13: TEC | B13: TEC-01 | C13: Measurement complexity | D13: =COUNTIF('Coding Log'!J:J,"TEC-01") -> 33 | E13: =COUNTIF('Coding Log'!K:K,"TEC-01") -> 5 | F13: =D13+E13 -> 38
A14: TEC | B14: TEC-02 | C14: Validation methodology gap | D14: =COUNTIF('Coding Log'!J:J,"TEC-02") -> 22 | E14: =COUNTIF('Coding Log'!K:K,"TEC-02") -> 5 | F14: =D14+E14 -> 27
A15: TEC | B15: TEC-03 | C15: Technical consensus failure | D15: =COUNTIF('Coding Log'!J:J,"TEC-03") -> 1 | E15: =COUNTIF('Coding Log'!K:K,"TEC-03") -> 0 | F15: =D15+E15 -> 1
A16: TEC | B16: TEC-04 | C16: Insufficient empirical base | D16: =COUNTIF('Coding Log'!J:J,"TEC-04") -> 5 | E16: =COUNTIF('Coding Log'!K:K,"TEC-04") -> 3 | F16: =D16+E16 -> 8
A17: TEC | B17: TEC-05 | C17: Tool heterogeneity | D17: =COUNTIF('Coding Log'!J:J,"TEC-05") -> 1 | E17: =COUNTIF('Coding Log'!K:K,"TEC-05") -> 1 | F17: =D17+E17 -> 2
A18: TEC | B18: TEC-06 | C18: Reproducibility barrier | D18: =COUNTIF('Coding Log'!J:J,"TEC-06") -> 2 | E18: =COUNTIF('Coding Log'!K:K,"TEC-06") -> 9 | F18: =D18+E18 -> 11
A19: Domain PRO
A20: PRO | B20: PRO-01 | C20: Comment period friction | D20: =COUNTIF('Coding Log'!J:J,"PRO-01") -> 11 | E20: =COUNTIF('Coding Log'!K:K,"PRO-01") -> 8 | F20: =D20+E20 -> 19
A21: PRO | B21: PRO-02 | C21: Process deadlock | D21: =COUNTIF('Coding Log'!J:J,"PRO-02") -> 4 | E21: =COUNTIF('Coding Log'!K:K,"PRO-02") -> 4 | F21: =D21+E21 -> 8
A22: PRO | B22: PRO-03 | C22: Revision cycle omission | D22: =COUNTIF('Coding Log'!J:J,"PRO-03") -> 11 | E22: =COUNTIF('Coding Log'!K:K,"PRO-03") -> 7 | F22: =D22+E22 -> 18
A23: PRO | B23: PRO-04 | C23: Deferred to future cycle | D23: =COUNTIF('Coding Log'!J:J,"PRO-04") -> 12 | E23: =COUNTIF('Coding Log'!K:K,"PRO-04") -> 6 | F23: =D23+E23 -> 18
A24: PRO | B24: PRO-05 | C24: Adoption / implementation barrier | D24: =COUNTIF('Coding Log'!J:J,"PRO-05") -> 0 | E24: =COUNTIF('Coding Log'!K:K,"PRO-05") -> 0 | F24: =D24+E24 -> 0
A25: PRO | B25: PRO-06 | C25: Standards coordination failure | D25: =COUNTIF('Coding Log'!J:J,"PRO-06") -> 5 | E25: =COUNTIF('Coding Log'!K:K,"PRO-06") -> 7 | F25: =D25+E25 -> 12
A26: Domain CRS
A27: CRS | B27: CRS-01 | C27: AI mentioned — no action | D27: =COUNTIF('Coding Log'!J:M,"CRS-01") -> 22 | E27: =COUNTIF('Coding Log'!K:K,"CRS-01") -> 1 | F27: =D27+E27 -> 23
A28: CRS | B28: CRS-02 | C28: Confidence language — non-prescriptive | D28: =COUNTIF('Coding Log'!J:M,"CRS-02") -> 54 | E28: =COUNTIF('Coding Log'!K:K,"CRS-02") -> 8 | F28: =D28+E28 -> 62
A29: CRS | B29: CRS-03 | C29: Future research called for | D29: =COUNTIF('Coding Log'!J:M,"CRS-03") -> 0 | E29: =COUNTIF('Coding Log'!K:K,"CRS-03") -> 0 | F29: =D29+E29 -> 0
A30: CRS | B30: CRS-04 | C30: Temporal marker — AI emergence | D30: =COUNTIF('Coding Log'!J:M,"CRS-04") -> 0 | E30: =COUNTIF('Coding Log'!K:K,"CRS-04") -> 0 | F30: =D30+E30 -> 0
A31: Domain EMER
A32: EMER | B32: EMER-01 | C32: [Emergent — add label] | D32: =COUNTIF('Coding Log'!J:J,"EMER-01") -> 0 | E32: =COUNTIF('Coding Log'!K:K,"EMER-01") -> 0 | F32: =D32+E32 -> 0
A33: EMER | B33: EMER-02 | C33: [Emergent — add label] | D33: =COUNTIF('Coding Log'!J:J,"EMER-02") -> 0 | E33: =COUNTIF('Coding Log'!K:K,"EMER-02") -> 0 | F33: =D33+E33 -> 0
A34: EMER | B34: EMER-03 | C34: [Emergent — add label] | D34: =COUNTIF('Coding Log'!J:J,"EMER-03") -> 0 | E34: =COUNTIF('Coding Log'!K:K,"EMER-03") -> 0 | F34: =D34+E34 -> 0
A35: EMER | B35: EMER-04 | C35: [Emergent — add label] | D35: =COUNTIF('Coding Log'!J:J,"EMER-04") -> 0 | E35: =COUNTIF('Coding Log'!K:K,"EMER-04") -> 0 | F35: =D35+E35 -> 0
A36: EMER | B36: EMER-05 | C36: [Emergent — add label] | D36: =COUNTIF('Coding Log'!J:J,"EMER-05") -> 0 | E36: =COUNTIF('Coding Log'!K:K,"EMER-05") -> 0 | F36: =D36+E36 -> 0
A37: GRAND TOTAL | D37: =SUM(D4:D36) -> 239 | E37: =SUM(E4:E36) -> 81 | F37: =SUM(F4:F36) -> 320

Sheet Q2 Rubric
A3: Domain | B3: Definition & scope | C3: Codes | D3: Passages coded
A4: ORG | B4: Captures institutional decisions, mandate boundaries, stakeholder dynamics, resource constraints, and organizational awareness gaps that explain why standards bodies chose not to — or could not — develop AI confidence guidance. Codes in this domain answer the question: who decided, and why? | C4: 7ORG-01 – ORG-07 | D4: 3931% of corpus
A5: Organizational barriers
A6: TEC | B6: Captures methodological, empirical, and tool-level obstacles to defining and validating AI confidence in forensic contexts. Includes measurement complexity, absent validation protocols, technical consensus failures, insufficient empirical evidence, tool heterogeneity, and reproducibility constraints. Codes answer: what technical problems prevent standards from being written? | C6: 6TEC-01 – TEC-06 | D6: 3628% of corpus
A7: Technical barriers
A8: PRO | B8: Captures failures within the formal standards development process itself — comment period friction, process deadlocks, revision cycle omissions, deliberate deferrals, adoption gaps, and cross-SDO coordination breakdowns. Codes answer: how did the process fail to produce or implement AI guidance? | C8: 6PRO-01 – PRO-06 | D8: 2318% of corpus
A9: Procedural barriers
A10: CRS | B10: Flag codes applied alongside primary ORG, TEC, or PRO codes — never used alone. Marks passages where AI is acknowledged without prescription, confidence language appears without operationalization, future research is called for, or AI is framed as temporally emergent. Codes answer: how does the gap manifest in language? | C10: 4CRS-01 – CRS-04 | D10: 3326% of corpus
A11: Cross-cutting flags
A12: Grand total — all domains | C12: 23 | D12: 1271

Sheet Decision Log
A1: Date | B1: Decisions
A2: ? | B2: Entry 2 (ORG-06): Coded. The legal consultation requirement is more than boilerplate here because it appears in the Limitations section as a structural constraint on operationalizing any AI guidance — it gates the entire document's applicability. Not removing the "?" entirely, but it stands as coded for Pass 1.
A3: ? | B3: Entry 4 (CRS-02 + TEC-02): Both coded. The "human verification required" language is CRS-02 (non-prescriptive). The absence of any verification protocol despite the stated need tips this into TEC-02 — SWGDE recognized validation was necessary but had no methodology to specify.
A4: ? | B4: Entry 7 (PRO-02): Coded as PRO-02. The 2.5-year cycle with 9 revision sessions producing only an awareness document — not a standard, not a position — is evidence of a process that could not converge on prescriptive content. PRO-04 would require explicit deferral language ("this will be addressed in a future document"), which is absent. PRO-02 is the right call.
A5: ? | B5: change Code 1 from PRO-02 to PRO-06. Write a one-line decision log entry explaining: "E3016-18 is an SDO-published standard that has not been accepted into the OSAC governance registry — this is a coordination failure between ASTM and OSAC, not an internal process stall. PRO-06 is more precise than PRO-02."
A6: 46125 | B6: Decision Log Entry — 2026-04-13 | Protocol Amendment — Reliability Design Modification Protocol Amendment — 2026-04-13: Intra-rater κ with 14-day gap (originally specified in Section IV, Phase 2 reliability) replaced by Lincoln & Guba (1985) dependability audit trail. Rationale: course submission deadline (April 28, 2026) structurally precludes the minimum 14-day gap required between Pass 1 and Pass 2 coding. The amendment does not alter the Applied Observational classification under Edgar & Manz (2017), the QUAN→QUAL design logic, or the codebook. Reliability evidence consists of: (1) nine analytic memos documenting pattern emergence and code boundary decisions; (2) decision log entries for all code boundary cases; (3) a stability check performed on five provisional entries (10, 11, 17, 18, 19) recoded without reference to Pass 1 notes (80% stability, exceeding ≥70% dependability threshold). Pass 2 κ calculation is scheduled for May 2, 2026 and will be reported as a post-submission reliability confirmation in the dissertation version of this analysis.
A7: 46125 | B7: 2026-04-13 | Protocol Amendment — Reliability Design Modification Protocol Amendment — 2026-04-13: Intra-rater κ with 14-day gap (originally specified in Section IV, Phase 2 reliability) replaced by Lincoln & Guba (1985) dependability audit trail. Rationale: course submission deadline (April 28, 2026) structurally precludes the minimum 14-day gap required between Pass 1 and Pass 2 coding. The amendment does not alter the Applied Observational classification under Edgar & Manz (2017), the QUAN→QUAL design logic, or the codebook. Reliability evidence consists of: (1) nine analytic memos documenting pattern emergence and code boundary decisions; (2) decision log entries for all code boundary cases; (3) a stability check performed on five provisional entries (10, 11, 17, 18, 19) recoded without reference to Pass 1 notes (80% stability, exceeding ≥70% dependability threshold). Pass 2 κ calculation is scheduled for May 2, 2026 and will be reported as a post-submission reliability confirmation in the dissertation version of this analysis.
A8: 46126 | B8: 1. Remove the May 2 Pass 2 κ reference entirely The April 13 Decision Log entry states Pass 2 κ is "scheduled for May 2, 2026 and will be reported as a post-submission reliability confirmation." With a hard April 28 deadline and no post-submission work permitted, that sentence is now inaccurate and must be corrected. The Lincoln & Guba dependability audit trail stands as your sole reliability mechanism — that is sufficient and already documented. Simply remove the May 2 reference from both the Decision Log and any methods language. (DONE) 2. Formally adopt purposive saturation sampling for corpus completion You cannot code all 35 remaining documents at full depth by April 28 and write the paper. You need to formally adopt purposive saturation sampling — a recognized qualitative design strategy — which means you stop coding new documents when no new codes are emerging, and you document that decision explicitly. This is methodologically legitimate under Lincoln & Guba and consistent with constant comparative method. Original Design Amended Design Corpus 47 docs, full coding κ subsample complete + saturation sampling Reliability Lincoln & Guba + May 2 κ Lincoln & Guba only (already documented) Stopping rule Code all documents Stop at saturation + κ docs complete Methodological basis Edgar & Manz (2017) Unchanged Defensibility Strong Still strong — saturation sampling is standard qualitative practice You are not weakening your study. Purposive saturation sampling is what qualitative researchers do when corpus depth matters more than corpus exhaustion. Your 12 coded documents already show saturated patterns across ORG-01, TEC-01, TEC-04, PRO-04, and EMER-01 — that is a finding, not a gap.
A9: 46129 | B9: Document TEC-04 as a late-emerging, empirically-gated code and proceed. Add a methodological note to the analysis chapter explaining why TEC-04 activated late (empirical documents are rare in the sub-corpus) and what that structure tells us (the AIDFIR gap includes a performance-reporting gap at the institutional level).
A10: 46129 | B10: See DLEmerging Pattern-Saturation Tab (Decision-Emrgng Patt Saturatn)
A11: 46130 | B11: 4/18/20262026-04-18 | Protocol Correction — κ-Subsample Roster Amendment (Path C, Doc #6 codebook-constitutive) Doc #6 (NIST SP 800-53 Rev. 5) is reclassified from κ-subsample member to codebook-constitutive and removed from the Lincoln & Guba (1985) dependability audit trail membership. Triggering realization: during Doc #6 coding (4/15/2026) and subsequent memo work (Memo #14), the document's nine coded entries were found to have participated in the definitional structure of the codebook rather than to have tested the codebook as a neutral instrument. Specifically, Entry 68 (RA-3(4) Predictive Cyber Analytics) produced the first TEC-06 activation for a NIST document, and Entry 67 (technology-neutral design principle) became the reference instance for the ORG-01 / TEC-02 / CRS-01 triple-code — both constituting code-boundary work rather than code-application. Rationale: primary justification is audit trail integrity under Lincoln & Guba — dependability requires a transparent record distinguishing codebook construction from codebook application, and codebook-constitutive documents belong in the construction record. Secondary justification is saturation validity — saturation was declared 4/17/2026 on the three-consecutive-zero-new-codes rule (Decision Log Amendment #2, 2026-04-14), and Doc #6's code-boundary contributions place it categorically within pre-saturation codebook construction even though chronologically coded late. Consequences: (1) Doc #6's nine coded entries (#63–#71) remain in the Coding Log as audit trail evidence but are excluded from frequency counts, saturation evidence, and cross-document pattern aggregation in Chapter 5; (2) κ-subsample roster becomes Docs #4, #10, #21, #25, #26, #28 (six documents); (3) six-document κ-subsample floor from Decision Log Amendment #2 (2026-04-14) remains preserved because the original roster was seven; (4) April 17 Saturation Declaration listing of "five remaining κ-subsample documents — Docs #4, #6, #21, #25, #28" is hereby corrected to four remaining κ-subsample documents — Docs #4, #21, #25, #28 — with Doc #6 reclassified per this entry. Cross-references: Memo #14 (documents Path C selection); Decision Log Amendment #1 (2026-04-13, Lincoln & Guba dependability audit trail); Decision Log Amendment #2 (2026-04-14, six-document κ-subsample floor); April 17 Saturation Declaration (Emerging Patterns sheet — requires update to reflect corrected κ-subsample roster).
A12: 46130 | B12: 2026-04-18 | Within-κ Methodological Decisions — Doc #4 Registry Anomaly (Path A) and Doc #28 Longitudinal-Pair Coding (Path A) Two within-κ coding decisions documented at coding time; neither alters the κ sample or the coding methodology. Doc #4 (Path A — registry anomaly). Registry row 4 records the title "NIST CSF 2.0 — Public Comment Analysis Report" and artifact type "Public Comment Record," but the registry URL points to the February 26, 2024 NIST CSF 2.0 release press release. Web search conducted 4/18/2026 confirmed no discrete standalone "NIST CSF 2.0 Public Comment Analysis Report" document exists; NIST's CSF 2.0 disposition model posted comments to the CSF 2.0 website and reflected feedback in redrafts rather than publishing a consolidated response-to-comments artifact. Path A selected by coder: the artifact identified by the registry URL was coded as Doc #4; the registry title and artifact-type fields are flagged for correction in a future registry maintenance pass. No Decision Log amendment is required because the κ sample and the artifact actually coded are unchanged; this is a metadata-field correction. The anomaly itself is dependability audit trail evidence — transparent documentation of a registry-integrity issue caught at coding time. Doc #28 (Path A — longitudinal-pair coding). Doc #28 (SWGDE 18-V-001-1.1, 3/22/2024) and Doc #21 (SWGDE 18-V-001-2.0, 12/10/2025) are the same document at two revision states, 21 months apart. The longitudinal pair was identified at coding time for Doc #28 (4/18/2026) based on shared SWGDE identifier, title, and Doc #21's revision-history table. Path A selected by coder: Part 1 rubric scored standalone per Phase 1 methodology (preserves independent QUAN scoring); Part 2 entries focused on revision-delta passages and v1.1-unique content; Part 3 memos framed as longitudinal analysis. Near-identical passages in both versions were not re-coded in Doc #28 (they were coded in Doc #21, entries #126–#136). Rationale: this approach preserves audit trail integrity — documents are independently scored for Phase 1 QUAN data — while avoiding redundant Part 2 entries on near-identical passages and enabling longitudinal analysis of revision-delta content. No Decision Log amendment is required because the κ sample and coding methodology are unchanged; this is a within-κ analytical approach adapted to the longitudinal pair. Longitudinal framing surfaces the revision-scope mechanism (structurally preserved gap through substantive revision), which standalone coding of both documents would have produced as two independent snapshots rather than as a single mechanism finding. Cross-references: Memo #23 (registry anomaly note, Doc #4); Memo on Doc #28 (longitudinal-pair methodology and primary findings); Decision Log Amendment #1 (2026-04-13, Lincoln & Guba dependability audit trail); Coding Log entries #126–#136 (Doc #21, near-identical passages coded for the pair).
A13: 46133 | B13: Decision Log Amendment #3 (2026-04-21) — EMER-01 Held Status Reconciliation The 2026-04-14 Decision Log entry listed EMER-01 alongside ORG-01, TEC-01, TEC-04, and PRO-04 as codes "likely to emerge as saturating by the end of coding." This was projective language regarding anticipated codebook outcomes, not a record of codes activated as of that date. The phrase "your 12 coded documents already show saturated patterns" in that entry is similarly understood as projective characterization; on 2026-04-14 the coding log contained approximately seven completed documents with Doc #6 in progress. Per Memo #4 (2026-04-10), EMER-01 (governmental policy reversal as external process barrier) was proposed as a candidate emergent code following Entry #19 (Doc #1, EO 14110 rescission rendering NIST AI RMF RFC archive inaccessible), with activation conditioned on evidence of recurrence across remaining documents. Per Memo #13 (2026-04-15), EMER-01 was held and not activated, a decision made one day after the 2026-04-14 projective language. Subsequent coding between 2026-04-15 and saturation declaration (2026-04-17) included Docs #6, #10, #20, and #13, during which EO 14110 and AI Action Plan references appear at Entries #98 (Doc #20, §1.2 scope exclusion) and #105 (Doc #13, §1 AI RMF revision footnote). These passages were coded to existing codes (ORG-01 and PRO-04 respectively) on the basis that the primary analytic weight of each passage sits with scope exclusion and deferred-to-future-cycle, with governmental-policy context serving as secondary framing. This coding decision is consistent with the EMER-01 hold under Memo #13. The coding log contains zero EMER-01 applications in Code 1, Code 2, Code 3, or CRS flag columns across 171 entries, consistent with Memo #13. The Saturation sheet text (Decision-Emrgng Patt Saturatn, row 30) previously stated EMER-01 was "saturated across five documents and five distinct manifestations." This text reflected the 2026-04-14 projective language rather than the 2026-04-15 held status and has been corrected (2026-04-21) to reflect the held decision. The single coded instance at Entry #19 is retained under existing codes PRO-02 and ORG-05. Decision record precedence: Memo #13 (held) supersedes the 2026-04-14 projective language. The coding log is authoritative for code application. The governmental policy reversal pattern is carried forward as a cross-document contextual theme in the Chapter 5 integration, where the code/theme distinction is methodologically legitimate per Lincoln and Guba (1985) and Saldaña (2021). Cross-references: Memo #4 (2026-04-10, Doc #1 access failure finding); Memo #13 (2026-04-15, EMER-01 hold confirmation); Coding Log Entries #19, #98, #105; Decision-Emrgng Patt Saturatn row 30 (corrected 2026-04-21).

Sheet Decision-Emrgng Patt Saturatn
A2: Emerging Patterns — Theoretical Saturation Declaration
A4: Date: April 17, 2026 Entry type: Saturation determination Methodological basis: Lincoln & Guba (1985); Morse (1995); per Decision Log Amendment #2 (2026-04-14)
A8: Declaration
A10: Theoretical saturation was reached in the Phase 2 inductive coding corpus on April 17, 2026. Three consecutive documents — Doc #7 (NIST SP 800-61r3, Incident Response), Doc #20 (NIST SP 800-218A, Secure Software Development Practices for Generative AI), and Doc #13 (NIST IR 8596, Cybersecurity Framework Profile for Artificial Intelligence) — produced zero new codes and zero refinements to existing code definitions. This satisfies the three-consecutive-document stopping rule established in Decision Log Amendment #2 (2026-04-14).
A14: Evidence of Saturation
A16: Trigger sequence | B16: Doc # | C16: Document | D16: Codes applied | E16: New codes | F16: Refinements
A17: 1 of 3 | B17: #7 | C17: NIST SP 800-61r3 (Incident Response) | D17: All from established codebook (entries 92–97, 6 entries) | E17: 0 | F17: 0
A18: 2 of 3 | B18: #20 | C18: NIST SP 800-218A (Secure Dev for GenAI) | D18: ORG-01, TEC-01, TEC-02, TEC-06, PRO-06, CRS-02 (entries 98–103, 6 entries) | E18: 0 | F18: 0
A19: 3 of 3 | B19: #13 | C19: NIST IR 8596 (Cyber AI Profile) | D19: ORG-01, TEC-01, TEC-02, TEC-06, PRO-03, PRO-04, CRS-01, CRS-02 (entries 104–110, 7 entries) | E19: 0 | F19: 0
A22: Saturated Codebook at Declaration
A24: The following codes were confirmed across multiple documents and sub-corpora prior to the saturation trigger:
A26: Organizational family: ORG-01 (scope exclusion / voluntary framing), ORG-05 (topical coverage gap), ORG-06 (admissibility/legal gap), ORG-07 (AI awareness gap)
A27: Technical family: TEC-01 (measurement complexity), TEC-02 (validation methodology gap), TEC-04 (benchmark/evaluation gap), TEC-06 (AI opacity / explainability barrier)
A28: Procedural family: PRO-01, PRO-03 (revision cycle omission), PRO-04 (deferred to future cycle), PRO-06 (methodology deference)
A29: Confidence-related (CRS) flags: CRS-01 (AI mentioned without action), CRS-02 (confidence language, non-prescriptive)
A30: Emergent code considered: EMER-01 (governmental policy reversal as external process barrier). Candidate emergent code proposed in Memo #4 (Doc #1, Entry #19, EO 14110 rescission) pending evidence of recurrence. Per Memo #13 (2026-04-15), EMER-01 was held and not activated. The single coded instance at Entry #19 was retained under existing codes PRO-02 + ORG-05. The coding log contains zero EMER-01 applications across 171 entries. Governmental policy reversal is carried forward as a cross-document contextual theme in the Chapter 5 integration rather than as an activated code. See Decision Log Amendment #3 (2026-04-21) for full reconciliation.
A34: Consequences of Declaration
A36: Per Decision Log Amendment #2 (2026-04-14):
A38: 1. Tier 2 saturation-sampling coding is closed. No additional non-κ documents will be coded. Remaining Tier 2 candidate documents (including NIST OpenMFC evaluation proceedings, additional SWGDE imaging documents, and revision history entries outside the κ subsample) are excluded from further coding.
A39: 2. Tier 1 κ-subsample coding continues. The remaining κ-subsample documents — originally identified as Docs #4, #6, #21, #25, #28 — will be coded regardless of saturation status, as they constitute the Lincoln & Guba dependability audit trail and are not subject to the saturation stopping rule. [UPDATED 2026-04-20: Per Decision Log entry 2026-04-18 (Path C), Doc #6 was reclassified as codebook-constitutive and removed from the κ-subsample roster. The final κ-subsample is Docs #4, #10, #21, #25, #26, #28 — six documents, preserving the Amendment #2 floor. All six are now coded. See Post-Saturation Coding Confirmation entry below.]
A40: 3. Codebook is frozen. No new codes or code refinements will be introduced during κ-subsample coding. Any novel patterns observed in the remaining κ documents will be documented as memo notes rather than new codes.
... A144: As of 2026-04-18, Phase 2 inductive QUAL coding is complete. Saturation was declared 2026-04-17 via the trigger sequence Doc #7 → Doc #20 → Doc #13 (three consecutive documents producing zero new codes). The κ-subsample floor of six documents (Decision Log Amendment #2) is satisfied by Docs #10, #26, #4, #21, #25, #28, all coded under a frozen codebook with zero new codes post-saturation. Doc #6 is reclassified as codebook-constitutive (Decision Log entry 2026-04-18, Path C). Total entries in Coding Log: 164 across 18 documents. Audit trail is complete under Lincoln & Guba (1985). Cross-phase integration with Phase 1 QUAN findings proceeds under the dissertation write-up schedule.

Sheet Emerging Patterns 1-4
A2: CHECK 3 — Emergent patterns
A4: Pattern 1 — PRO-06 for E3016-18 (entry 23):
A6: This is the clearest emergent code candidate in your corpus. ANSI/ASTM E3016-18 "Standard Guide for Establishing Confidence in Digital and Multimedia Evidence Forensic Results by Error Mitigation Analysis" was published by ASTM in 2018 and has been pending OSAC Registry acceptance for 6+ years with no resolution. This is not PRO-02 (internal process stall) — the standard was published by an SDO but never accepted into the governance registry. The barrier is specifically a coordination failure between ASTM (the SDO that published it) and OSAC (the governance body that has not accepted it). That is PRO-06 (standards coordination failure) — the definition you already have.
A8: Action: Recode entry 23 from PRO-02 to PRO-06, or assign both. PRO-06 is more precise here because the standard exists and is published — the failure is in the adoption pathway between the SDO and the governance registry, which is a coordination gap rather than a process stall. Write a decision log entry explaining this distinction.
A10: Pattern 2 — CRS flag formulas are broken:
A12: Your Code Frequency sheet is not counting CRS flags correctly. The actual CRS-02 count is 7 and CRS-01 count is 2 but your sheet shows zeros for both. This needs to be fixed before your κ analysis or your frequency report will undercount the most common flag in your corpus.
A14: Pattern 3 — Rationale columns are mostly blank:
A16: The Code 1 rationale and Code 2 rationale columns (columns N and O) are blank for most entries — the text "Strong," "Provisional ?", and similar notes are appearing in the memo column instead. This is not a methodological problem but it will make Pass 2 reconciliation harder. In your next coding session, try entering a one-sentence rationale in column N for each new entry so the reasoning is captured at the passage level rather than only in the memo.
A18: Pattern 4 — Governmental policy reversal as distinct barrier type:
A20: Entry 19 (EO 14110 rescission rendering NIST AI RMF RFC inaccessible) does not fit cleanly into any existing code. PRO-02 + ORG-05 captures it partially but misses the specifically political and external nature of the barrier. This is still a candidate for EMER-01. The question is whether this pattern recurs. If you find other instances of AI governance records being rendered inaccessible by political action in your remaining 42 documents, activate EMER-01. If entry 19 remains the only instance, it is better described as an unusual PRO-02 than as a new category. Hold EMER-01 — do not activate yet.
